package com.google.android.gms.ads.identifier;

import java.util.Map;

final class a
  extends Thread
{
  a(AdvertisingIdClient paramAdvertisingIdClient, Map paramMap) {}
  
  /* Error */
  public final void run()
  {
    // Byte code:
    //   0: new 22	com/google/android/gms/ads/identifier/zzc
    //   3: dup
    //   4: invokespecial 23	com/google/android/gms/ads/identifier/zzc:<init>	()V
    //   7: pop
    //   8: aload_0
    //   9: getfield 10	com/google/android/gms/ads/identifier/a:a	Ljava/util/Map;
    //   12: astore_2
    //   13: ldc 25
    //   15: invokestatic 31	android/net/Uri:parse	(Ljava/lang/String;)Landroid/net/Uri;
    //   18: invokevirtual 35	android/net/Uri:buildUpon	()Landroid/net/Uri$Builder;
    //   21: astore_3
    //   22: aload_2
    //   23: invokeinterface 41 1 0
    //   28: invokeinterface 47 1 0
    //   33: astore 4
    //   35: aload 4
    //   37: invokeinterface 53 1 0
    //   42: ifeq +36 -> 78
    //   45: aload 4
    //   47: invokeinterface 57 1 0
    //   52: checkcast 59	java/lang/String
    //   55: astore 16
    //   57: aload_3
    //   58: aload 16
    //   60: aload_2
    //   61: aload 16
    //   63: invokeinterface 63 2 0
    //   68: checkcast 59	java/lang/String
    //   71: invokevirtual 69	android/net/Uri$Builder:appendQueryParameter	(Ljava/lang/String;Ljava/lang/String;)Landroid/net/Uri$Builder;
    //   74: pop
    //   75: goto -40 -> 35
    //   78: aload_3
    //   79: invokevirtual 73	android/net/Uri$Builder:build	()Landroid/net/Uri;
    //   82: invokevirtual 77	android/net/Uri:toString	()Ljava/lang/String;
    //   85: astore 5
    //   87: new 79	java/net/URL
    //   90: dup
    //   91: aload 5
    //   93: invokespecial 82	java/net/URL:<init>	(Ljava/lang/String;)V
    //   96: invokevirtual 86	java/net/URL:openConnection	()Ljava/net/URLConnection;
    //   99: checkcast 88	java/net/HttpURLConnection
    //   102: astore 12
    //   104: aload 12
    //   106: invokevirtual 92	java/net/HttpURLConnection:getResponseCode	()I
    //   109: istore 14
    //   111: iload 14
    //   113: sipush 200
    //   116: if_icmplt +11 -> 127
    //   119: iload 14
    //   121: sipush 300
    //   124: if_icmplt +50 -> 174
    //   127: ldc 94
    //   129: new 96	java/lang/StringBuilder
    //   132: dup
    //   133: bipush 65
    //   135: aload 5
    //   137: invokestatic 100	java/lang/String:valueOf	(Ljava/lang/Object;)Ljava/lang/String;
    //   140: invokevirtual 103	java/lang/String:length	()I
    //   143: iadd
    //   144: invokespecial 106	java/lang/StringBuilder:<init>	(I)V
    //   147: ldc 108
    //   149: invokevirtual 112	java/lang/StringBuilder:append	(Ljava/lang/String;)Ljava/lang/StringBuilder;
    //   152: iload 14
    //   154: invokevirtual 115	java/lang/StringBuilder:append	(I)Ljava/lang/StringBuilder;
    //   157: ldc 117
    //   159: invokevirtual 112	java/lang/StringBuilder:append	(Ljava/lang/String;)Ljava/lang/StringBuilder;
    //   162: aload 5
    //   164: invokevirtual 112	java/lang/StringBuilder:append	(Ljava/lang/String;)Ljava/lang/StringBuilder;
    //   167: invokevirtual 118	java/lang/StringBuilder:toString	()Ljava/lang/String;
    //   170: invokestatic 124	android/util/Log:w	(Ljava/lang/String;Ljava/lang/String;)I
    //   173: pop
    //   174: aload 12
    //   176: invokevirtual 127	java/net/HttpURLConnection:disconnect	()V
    //   179: return
    //   180: astore 13
    //   182: aload 12
    //   184: invokevirtual 127	java/net/HttpURLConnection:disconnect	()V
    //   187: aload 13
    //   189: athrow
    //   190: astore 9
    //   192: aload 9
    //   194: invokevirtual 130	java/lang/IndexOutOfBoundsException:getMessage	()Ljava/lang/String;
    //   197: astore 10
    //   199: ldc 94
    //   201: new 96	java/lang/StringBuilder
    //   204: dup
    //   205: bipush 32
    //   207: aload 5
    //   209: invokestatic 100	java/lang/String:valueOf	(Ljava/lang/Object;)Ljava/lang/String;
    //   212: invokevirtual 103	java/lang/String:length	()I
    //   215: iadd
    //   216: aload 10
    //   218: invokestatic 100	java/lang/String:valueOf	(Ljava/lang/Object;)Ljava/lang/String;
    //   221: invokevirtual 103	java/lang/String:length	()I
    //   224: iadd
    //   225: invokespecial 106	java/lang/StringBuilder:<init>	(I)V
    //   228: ldc 132
    //   230: invokevirtual 112	java/lang/StringBuilder:append	(Ljava/lang/String;)Ljava/lang/StringBuilder;
    //   233: aload 5
    //   235: invokevirtual 112	java/lang/StringBuilder:append	(Ljava/lang/String;)Ljava/lang/StringBuilder;
    //   238: ldc 134
    //   240: invokevirtual 112	java/lang/StringBuilder:append	(Ljava/lang/String;)Ljava/lang/StringBuilder;
    //   243: aload 10
    //   245: invokevirtual 112	java/lang/StringBuilder:append	(Ljava/lang/String;)Ljava/lang/StringBuilder;
    //   248: invokevirtual 118	java/lang/StringBuilder:toString	()Ljava/lang/String;
    //   251: aload 9
    //   253: invokestatic 137	android/util/Log:w	(Ljava/lang/String;Ljava/lang/String;Ljava/lang/Throwable;)I
    //   256: pop
    //   257: return
    //   258: astore 6
    //   260: aload 6
    //   262: invokevirtual 140	java/lang/Exception:getMessage	()Ljava/lang/String;
    //   265: astore 7
    //   267: ldc 94
    //   269: new 96	java/lang/StringBuilder
    //   272: dup
    //   273: bipush 27
    //   275: aload 5
    //   277: invokestatic 100	java/lang/String:valueOf	(Ljava/lang/Object;)Ljava/lang/String;
    //   280: invokevirtual 103	java/lang/String:length	()I
    //   283: iadd
    //   284: aload 7
    //   286: invokestatic 100	java/lang/String:valueOf	(Ljava/lang/Object;)Ljava/lang/String;
    //   289: invokevirtual 103	java/lang/String:length	()I
    //   292: iadd
    //   293: invokespecial 106	java/lang/StringBuilder:<init>	(I)V
    //   296: ldc 142
    //   298: invokevirtual 112	java/lang/StringBuilder:append	(Ljava/lang/String;)Ljava/lang/StringBuilder;
    //   301: aload 5
    //   303: invokevirtual 112	java/lang/StringBuilder:append	(Ljava/lang/String;)Ljava/lang/StringBuilder;
    //   306: ldc 134
    //   308: invokevirtual 112	java/lang/StringBuilder:append	(Ljava/lang/String;)Ljava/lang/StringBuilder;
    //   311: aload 7
    //   313: invokevirtual 112	java/lang/StringBuilder:append	(Ljava/lang/String;)Ljava/lang/StringBuilder;
    //   316: invokevirtual 118	java/lang/StringBuilder:toString	()Ljava/lang/String;
    //   319: aload 6
    //   321: invokestatic 137	android/util/Log:w	(Ljava/lang/String;Ljava/lang/String;Ljava/lang/Throwable;)I
    //   324: pop
    //   325: return
    //   326: astore 6
    //   328: goto -68 -> 260
    // Local variable table:
    //   start	length	slot	name	signature
    //   0	331	0	this	a
    //   12	49	2	localMap	Map
    //   21	58	3	localBuilder	android.net.Uri.Builder
    //   33	13	4	localIterator	java.util.Iterator
    //   85	217	5	str1	java.lang.String
    //   258	62	6	localRuntimeException	java.lang.RuntimeException
    //   326	1	6	localIOException	java.io.IOException
    //   265	47	7	str2	java.lang.String
    //   190	62	9	localIndexOutOfBoundsException	java.lang.IndexOutOfBoundsException
    //   197	47	10	str3	java.lang.String
    //   102	81	12	localHttpURLConnection	java.net.HttpURLConnection
    //   180	8	13	localObject	java.lang.Object
    //   109	44	14	i	int
    //   55	7	16	str4	java.lang.String
    // Exception table:
    //   from	to	target	type
    //   104	111	180	finally
    //   127	174	180	finally
    //   87	104	190	java/lang/IndexOutOfBoundsException
    //   174	179	190	java/lang/IndexOutOfBoundsException
    //   182	190	190	java/lang/IndexOutOfBoundsException
    //   87	104	258	java/lang/RuntimeException
    //   174	179	258	java/lang/RuntimeException
    //   182	190	258	java/lang/RuntimeException
    //   87	104	326	java/io/IOException
    //   174	179	326	java/io/IOException
    //   182	190	326	java/io/IOException
  }
}


/* Location:           C:\Users\IrfanRZ\Desktop\video walp\classes_dex2jar.jar
 * Qualified Name:     com.google.android.gms.ads.identifier.a
 * JD-Core Version:    0.7.0.1
 */