package com.google.android.gms.internal.ads;

final class afz
  implements Runnable
{
  /* Error */
  public final void run()
  {
    // Byte code:
    //   0: ldc 17
    //   2: invokestatic 23	java/security/MessageDigest:getInstance	(Ljava/lang/String;)Ljava/security/MessageDigest;
    //   5: invokestatic 29	com/google/android/gms/internal/ads/afx:a	(Ljava/security/MessageDigest;)Ljava/security/MessageDigest;
    //   8: pop
    //   9: getstatic 32	com/google/android/gms/internal/ads/afx:a	Ljava/util/concurrent/CountDownLatch;
    //   12: invokevirtual 37	java/util/concurrent/CountDownLatch:countDown	()V
    //   15: return
    //   16: astore_2
    //   17: getstatic 32	com/google/android/gms/internal/ads/afx:a	Ljava/util/concurrent/CountDownLatch;
    //   20: invokevirtual 37	java/util/concurrent/CountDownLatch:countDown	()V
    //   23: return
    //   24: astore_1
    //   25: getstatic 32	com/google/android/gms/internal/ads/afx:a	Ljava/util/concurrent/CountDownLatch;
    //   28: invokevirtual 37	java/util/concurrent/CountDownLatch:countDown	()V
    //   31: aload_1
    //   32: athrow
    // Local variable table:
    //   start	length	slot	name	signature
    //   0	33	0	this	afz
    //   24	8	1	localObject	Object
    //   16	1	2	localNoSuchAlgorithmException	java.security.NoSuchAlgorithmException
    // Exception table:
    //   from	to	target	type
    //   0	9	16	java/security/NoSuchAlgorithmException
    //   0	9	24	finally
  }
}


/* Location:           C:\Users\IrfanRZ\Desktop\video walp\classes_dex2jar.jar
 * Qualified Name:     com.google.android.gms.internal.ads.afz
 * JD-Core Version:    0.7.0.1
 */