package com.google.android.gms.internal.ads;

import java.util.HashMap;
import java.util.List;
import java.util.Map;

final class ajq
  implements axs
{
  private final Map<String, List<avs<?>>> a = new HashMap();
  private final aho b;
  
  ajq(aho paramaho)
  {
    this.b = paramaho;
  }
  
  /* Error */
  private final boolean b(avs<?> paramavs)
  {
    // Byte code:
    //   0: aload_0
    //   1: monitorenter
    //   2: aload_1
    //   3: invokevirtual 33	com/google/android/gms/internal/ads/avs:e	()Ljava/lang/String;
    //   6: astore_3
    //   7: aload_0
    //   8: getfield 21	com/google/android/gms/internal/ads/ajq:a	Ljava/util/Map;
    //   11: aload_3
    //   12: invokeinterface 39 2 0
    //   17: ifeq +87 -> 104
    //   20: aload_0
    //   21: getfield 21	com/google/android/gms/internal/ads/ajq:a	Ljava/util/Map;
    //   24: aload_3
    //   25: invokeinterface 43 2 0
    //   30: checkcast 45	java/util/List
    //   33: astore 7
    //   35: aload 7
    //   37: ifnonnull +12 -> 49
    //   40: new 47	java/util/ArrayList
    //   43: dup
    //   44: invokespecial 48	java/util/ArrayList:<init>	()V
    //   47: astore 7
    //   49: aload_1
    //   50: ldc 50
    //   52: invokevirtual 53	com/google/android/gms/internal/ads/avs:b	(Ljava/lang/String;)V
    //   55: aload 7
    //   57: aload_1
    //   58: invokeinterface 56 2 0
    //   63: pop
    //   64: aload_0
    //   65: getfield 21	com/google/android/gms/internal/ads/ajq:a	Ljava/util/Map;
    //   68: aload_3
    //   69: aload 7
    //   71: invokeinterface 60 3 0
    //   76: pop
    //   77: getstatic 65	com/google/android/gms/internal/ads/eb:a	Z
    //   80: ifeq +16 -> 96
    //   83: ldc 67
    //   85: iconst_1
    //   86: anewarray 4	java/lang/Object
    //   89: dup
    //   90: iconst_0
    //   91: aload_3
    //   92: aastore
    //   93: invokestatic 70	com/google/android/gms/internal/ads/eb:b	(Ljava/lang/String;[Ljava/lang/Object;)V
    //   96: iconst_1
    //   97: istore 6
    //   99: aload_0
    //   100: monitorexit
    //   101: iload 6
    //   103: ireturn
    //   104: aload_0
    //   105: getfield 21	com/google/android/gms/internal/ads/ajq:a	Ljava/util/Map;
    //   108: aload_3
    //   109: aconst_null
    //   110: invokeinterface 60 3 0
    //   115: pop
    //   116: aload_1
    //   117: aload_0
    //   118: invokevirtual 73	com/google/android/gms/internal/ads/avs:a	(Lcom/google/android/gms/internal/ads/axs;)V
    //   121: getstatic 65	com/google/android/gms/internal/ads/eb:a	Z
    //   124: istore 5
    //   126: iconst_0
    //   127: istore 6
    //   129: iload 5
    //   131: ifeq -32 -> 99
    //   134: ldc 75
    //   136: iconst_1
    //   137: anewarray 4	java/lang/Object
    //   140: dup
    //   141: iconst_0
    //   142: aload_3
    //   143: aastore
    //   144: invokestatic 70	com/google/android/gms/internal/ads/eb:b	(Ljava/lang/String;[Ljava/lang/Object;)V
    //   147: iconst_0
    //   148: istore 6
    //   150: goto -51 -> 99
    //   153: astore_2
    //   154: aload_0
    //   155: monitorexit
    //   156: aload_2
    //   157: athrow
    // Local variable table:
    //   start	length	slot	name	signature
    //   0	158	0	this	ajq
    //   0	158	1	paramavs	avs<?>
    //   153	4	2	localObject1	Object
    //   6	137	3	str	String
    //   124	6	5	bool1	boolean
    //   97	52	6	bool2	boolean
    //   33	37	7	localObject2	Object
    // Exception table:
    //   from	to	target	type
    //   2	35	153	finally
    //   40	49	153	finally
    //   49	96	153	finally
    //   104	126	153	finally
    //   134	147	153	finally
  }
  
  /* Error */
  public final void a(avs<?> paramavs)
  {
    // Byte code:
    //   0: aload_0
    //   1: monitorenter
    //   2: aload_1
    //   3: invokevirtual 33	com/google/android/gms/internal/ads/avs:e	()Ljava/lang/String;
    //   6: astore_3
    //   7: aload_0
    //   8: getfield 21	com/google/android/gms/internal/ads/ajq:a	Ljava/util/Map;
    //   11: aload_3
    //   12: invokeinterface 81 2 0
    //   17: checkcast 45	java/util/List
    //   20: astore 4
    //   22: aload 4
    //   24: ifnull +97 -> 121
    //   27: aload 4
    //   29: invokeinterface 85 1 0
    //   34: ifne +87 -> 121
    //   37: getstatic 65	com/google/android/gms/internal/ads/eb:a	Z
    //   40: ifeq +35 -> 75
    //   43: iconst_2
    //   44: anewarray 4	java/lang/Object
    //   47: astore 9
    //   49: aload 9
    //   51: iconst_0
    //   52: aload 4
    //   54: invokeinterface 89 1 0
    //   59: invokestatic 95	java/lang/Integer:valueOf	(I)Ljava/lang/Integer;
    //   62: aastore
    //   63: aload 9
    //   65: iconst_1
    //   66: aload_3
    //   67: aastore
    //   68: ldc 97
    //   70: aload 9
    //   72: invokestatic 99	com/google/android/gms/internal/ads/eb:a	(Ljava/lang/String;[Ljava/lang/Object;)V
    //   75: aload 4
    //   77: iconst_0
    //   78: invokeinterface 102 2 0
    //   83: checkcast 29	com/google/android/gms/internal/ads/avs
    //   86: astore 5
    //   88: aload_0
    //   89: getfield 21	com/google/android/gms/internal/ads/ajq:a	Ljava/util/Map;
    //   92: aload_3
    //   93: aload 4
    //   95: invokeinterface 60 3 0
    //   100: pop
    //   101: aload 5
    //   103: aload_0
    //   104: invokevirtual 73	com/google/android/gms/internal/ads/avs:a	(Lcom/google/android/gms/internal/ads/axs;)V
    //   107: aload_0
    //   108: getfield 23	com/google/android/gms/internal/ads/ajq:b	Lcom/google/android/gms/internal/ads/aho;
    //   111: invokestatic 107	com/google/android/gms/internal/ads/aho:a	(Lcom/google/android/gms/internal/ads/aho;)Ljava/util/concurrent/BlockingQueue;
    //   114: aload 5
    //   116: invokeinterface 112 2 0
    //   121: aload_0
    //   122: monitorexit
    //   123: return
    //   124: astore 7
    //   126: iconst_1
    //   127: anewarray 4	java/lang/Object
    //   130: astore 8
    //   132: aload 8
    //   134: iconst_0
    //   135: aload 7
    //   137: invokevirtual 115	java/lang/InterruptedException:toString	()Ljava/lang/String;
    //   140: aastore
    //   141: ldc 117
    //   143: aload 8
    //   145: invokestatic 120	com/google/android/gms/internal/ads/eb:c	(Ljava/lang/String;[Ljava/lang/Object;)V
    //   148: invokestatic 126	java/lang/Thread:currentThread	()Ljava/lang/Thread;
    //   151: invokevirtual 129	java/lang/Thread:interrupt	()V
    //   154: aload_0
    //   155: getfield 23	com/google/android/gms/internal/ads/ajq:b	Lcom/google/android/gms/internal/ads/aho;
    //   158: invokevirtual 131	com/google/android/gms/internal/ads/aho:a	()V
    //   161: goto -40 -> 121
    //   164: astore_2
    //   165: aload_0
    //   166: monitorexit
    //   167: aload_2
    //   168: athrow
    // Local variable table:
    //   start	length	slot	name	signature
    //   0	169	0	this	ajq
    //   0	169	1	paramavs	avs<?>
    //   164	4	2	localObject	Object
    //   6	87	3	str	String
    //   20	74	4	localList	List
    //   86	29	5	localavs	avs
    //   124	12	7	localInterruptedException	java.lang.InterruptedException
    //   130	14	8	arrayOfObject1	Object[]
    //   47	24	9	arrayOfObject2	Object[]
    // Exception table:
    //   from	to	target	type
    //   107	121	124	java/lang/InterruptedException
    //   2	22	164	finally
    //   27	75	164	finally
    //   75	107	164	finally
    //   107	121	164	finally
    //   126	161	164	finally
  }
  
  /* Error */
  public final void a(avs<?> paramavs, bbw<?> parambbw)
  {
    // Byte code:
    //   0: aload_2
    //   1: getfield 137	com/google/android/gms/internal/ads/bbw:b	Lcom/google/android/gms/internal/ads/agn;
    //   4: ifnull +13 -> 17
    //   7: aload_2
    //   8: getfield 137	com/google/android/gms/internal/ads/bbw:b	Lcom/google/android/gms/internal/ads/agn;
    //   11: invokevirtual 141	com/google/android/gms/internal/ads/agn:a	()Z
    //   14: ifeq +9 -> 23
    //   17: aload_0
    //   18: aload_1
    //   19: invokevirtual 143	com/google/android/gms/internal/ads/ajq:a	(Lcom/google/android/gms/internal/ads/avs;)V
    //   22: return
    //   23: aload_1
    //   24: invokevirtual 33	com/google/android/gms/internal/ads/avs:e	()Ljava/lang/String;
    //   27: astore_3
    //   28: aload_0
    //   29: monitorenter
    //   30: aload_0
    //   31: getfield 21	com/google/android/gms/internal/ads/ajq:a	Ljava/util/Map;
    //   34: aload_3
    //   35: invokeinterface 81 2 0
    //   40: checkcast 45	java/util/List
    //   43: astore 5
    //   45: aload_0
    //   46: monitorexit
    //   47: aload 5
    //   49: ifnull -27 -> 22
    //   52: getstatic 65	com/google/android/gms/internal/ads/eb:a	Z
    //   55: ifeq +35 -> 90
    //   58: iconst_2
    //   59: anewarray 4	java/lang/Object
    //   62: astore 8
    //   64: aload 8
    //   66: iconst_0
    //   67: aload 5
    //   69: invokeinterface 89 1 0
    //   74: invokestatic 95	java/lang/Integer:valueOf	(I)Ljava/lang/Integer;
    //   77: aastore
    //   78: aload 8
    //   80: iconst_1
    //   81: aload_3
    //   82: aastore
    //   83: ldc 145
    //   85: aload 8
    //   87: invokestatic 99	com/google/android/gms/internal/ads/eb:a	(Ljava/lang/String;[Ljava/lang/Object;)V
    //   90: aload 5
    //   92: invokeinterface 149 1 0
    //   97: astore 6
    //   99: aload 6
    //   101: invokeinterface 154 1 0
    //   106: ifeq -84 -> 22
    //   109: aload 6
    //   111: invokeinterface 158 1 0
    //   116: checkcast 29	com/google/android/gms/internal/ads/avs
    //   119: astore 7
    //   121: aload_0
    //   122: getfield 23	com/google/android/gms/internal/ads/ajq:b	Lcom/google/android/gms/internal/ads/aho;
    //   125: invokestatic 161	com/google/android/gms/internal/ads/aho:b	(Lcom/google/android/gms/internal/ads/aho;)Lcom/google/android/gms/internal/ads/b;
    //   128: aload 7
    //   130: aload_2
    //   131: invokeinterface 165 3 0
    //   136: goto -37 -> 99
    //   139: astore 4
    //   141: aload_0
    //   142: monitorexit
    //   143: aload 4
    //   145: athrow
    // Local variable table:
    //   start	length	slot	name	signature
    //   0	146	0	this	ajq
    //   0	146	1	paramavs	avs<?>
    //   0	146	2	parambbw	bbw<?>
    //   27	55	3	str	String
    //   139	5	4	localObject	Object
    //   43	48	5	localList	List
    //   97	13	6	localIterator	java.util.Iterator
    //   119	10	7	localavs	avs
    //   62	24	8	arrayOfObject	Object[]
    // Exception table:
    //   from	to	target	type
    //   30	47	139	finally
    //   141	143	139	finally
  }
}


/* Location:           C:\Users\IrfanRZ\Desktop\video walp\classes_dex2jar.jar
 * Qualified Name:     com.google.android.gms.internal.ads.ajq
 * JD-Core Version:    0.7.0.1
 */