package com.google.android.gms.internal.ads;

import android.content.Context;
import com.google.android.gms.ads.internal.zzbc;
import java.util.concurrent.Future;

@cm
public final class aw
  extends iz
{
  private final ap a;
  private final zzaej b;
  private final ik c;
  private final ay d;
  private final Object e = new Object();
  private Future<ij> f;
  
  public aw(Context paramContext, zzbc paramzzbc, ik paramik, agw paramagw, ap paramap, asn paramasn)
  {
    this(paramik, paramap, new ay(paramContext, paramzzbc, new kx(paramContext), paramagw, paramik, paramasn));
  }
  
  private aw(ik paramik, ap paramap, ay paramay)
  {
    this.c = paramik;
    this.b = paramik.b;
    this.a = paramap;
    this.d = paramay;
  }
  
  /* Error */
  public final void a()
  {
    // Byte code:
    //   0: bipush 254
    //   2: istore_1
    //   3: aload_0
    //   4: getfield 41	com/google/android/gms/internal/ads/aw:e	Ljava/lang/Object;
    //   7: astore 9
    //   9: aload 9
    //   11: monitorenter
    //   12: aload_0
    //   13: aload_0
    //   14: getfield 52	com/google/android/gms/internal/ads/aw:d	Lcom/google/android/gms/internal/ads/ay;
    //   17: invokestatic 66	com/google/android/gms/internal/ads/jl:a	(Ljava/util/concurrent/Callable;)Lcom/google/android/gms/internal/ads/ne;
    //   20: putfield 68	com/google/android/gms/internal/ads/aw:f	Ljava/util/concurrent/Future;
    //   23: aload 9
    //   25: monitorexit
    //   26: aload_0
    //   27: getfield 68	com/google/android/gms/internal/ads/aw:f	Ljava/util/concurrent/Future;
    //   30: ldc2_w 69
    //   33: getstatic 76	java/util/concurrent/TimeUnit:MILLISECONDS	Ljava/util/concurrent/TimeUnit;
    //   36: invokeinterface 82 4 0
    //   41: checkcast 84	com/google/android/gms/internal/ads/ij
    //   44: astore_3
    //   45: aload_3
    //   46: ifnull +79 -> 125
    //   49: getstatic 89	com/google/android/gms/internal/ads/jn:a	Landroid/os/Handler;
    //   52: new 91	com/google/android/gms/internal/ads/ax
    //   55: dup
    //   56: aload_0
    //   57: aload_3
    //   58: invokespecial 94	com/google/android/gms/internal/ads/ax:<init>	(Lcom/google/android/gms/internal/ads/aw;Lcom/google/android/gms/internal/ads/ij;)V
    //   61: invokevirtual 100	android/os/Handler:post	(Ljava/lang/Runnable;)Z
    //   64: pop
    //   65: return
    //   66: astore 10
    //   68: aload 9
    //   70: monitorexit
    //   71: aload 10
    //   73: athrow
    //   74: astore 7
    //   76: ldc 102
    //   78: invokestatic 107	com/google/android/gms/internal/ads/je:e	(Ljava/lang/String;)V
    //   81: iconst_2
    //   82: istore_1
    //   83: aload_0
    //   84: getfield 68	com/google/android/gms/internal/ads/aw:f	Ljava/util/concurrent/Future;
    //   87: iconst_1
    //   88: invokeinterface 111 2 0
    //   93: pop
    //   94: aconst_null
    //   95: astore_3
    //   96: goto -51 -> 45
    //   99: astore 6
    //   101: aconst_null
    //   102: astore_3
    //   103: iconst_0
    //   104: istore_1
    //   105: goto -60 -> 45
    //   108: astore 5
    //   110: aconst_null
    //   111: astore_3
    //   112: iconst_0
    //   113: istore_1
    //   114: goto -69 -> 45
    //   117: astore_2
    //   118: aconst_null
    //   119: astore_3
    //   120: iconst_0
    //   121: istore_1
    //   122: goto -77 -> 45
    //   125: new 84	com/google/android/gms/internal/ads/ij
    //   128: dup
    //   129: aload_0
    //   130: getfield 43	com/google/android/gms/internal/ads/aw:c	Lcom/google/android/gms/internal/ads/ik;
    //   133: getfield 114	com/google/android/gms/internal/ads/ik:a	Lcom/google/android/gms/internal/ads/zzaef;
    //   136: getfield 119	com/google/android/gms/internal/ads/zzaef:c	Lcom/google/android/gms/internal/ads/zzjj;
    //   139: aconst_null
    //   140: aconst_null
    //   141: iload_1
    //   142: aconst_null
    //   143: aconst_null
    //   144: aload_0
    //   145: getfield 48	com/google/android/gms/internal/ads/aw:b	Lcom/google/android/gms/internal/ads/zzaej;
    //   148: getfield 125	com/google/android/gms/internal/ads/zzaej:k	I
    //   151: aload_0
    //   152: getfield 48	com/google/android/gms/internal/ads/aw:b	Lcom/google/android/gms/internal/ads/zzaej;
    //   155: getfield 129	com/google/android/gms/internal/ads/zzaej:j	J
    //   158: aload_0
    //   159: getfield 43	com/google/android/gms/internal/ads/aw:c	Lcom/google/android/gms/internal/ads/ik;
    //   162: getfield 114	com/google/android/gms/internal/ads/ik:a	Lcom/google/android/gms/internal/ads/zzaef;
    //   165: getfield 133	com/google/android/gms/internal/ads/zzaef:i	Ljava/lang/String;
    //   168: iconst_0
    //   169: aconst_null
    //   170: aconst_null
    //   171: aconst_null
    //   172: aconst_null
    //   173: aconst_null
    //   174: aload_0
    //   175: getfield 48	com/google/android/gms/internal/ads/aw:b	Lcom/google/android/gms/internal/ads/zzaej;
    //   178: getfield 136	com/google/android/gms/internal/ads/zzaej:h	J
    //   181: aload_0
    //   182: getfield 43	com/google/android/gms/internal/ads/aw:c	Lcom/google/android/gms/internal/ads/ik;
    //   185: getfield 139	com/google/android/gms/internal/ads/ik:d	Lcom/google/android/gms/internal/ads/zzjn;
    //   188: aload_0
    //   189: getfield 48	com/google/android/gms/internal/ads/aw:b	Lcom/google/android/gms/internal/ads/zzaej;
    //   192: getfield 141	com/google/android/gms/internal/ads/zzaej:f	J
    //   195: aload_0
    //   196: getfield 43	com/google/android/gms/internal/ads/aw:c	Lcom/google/android/gms/internal/ads/ik;
    //   199: getfield 142	com/google/android/gms/internal/ads/ik:f	J
    //   202: aload_0
    //   203: getfield 48	com/google/android/gms/internal/ads/aw:b	Lcom/google/android/gms/internal/ads/zzaej;
    //   206: getfield 145	com/google/android/gms/internal/ads/zzaej:m	J
    //   209: aload_0
    //   210: getfield 48	com/google/android/gms/internal/ads/aw:b	Lcom/google/android/gms/internal/ads/zzaej;
    //   213: getfield 148	com/google/android/gms/internal/ads/zzaej:n	Ljava/lang/String;
    //   216: aload_0
    //   217: getfield 43	com/google/android/gms/internal/ads/aw:c	Lcom/google/android/gms/internal/ads/ik;
    //   220: getfield 151	com/google/android/gms/internal/ads/ik:h	Lorg/json/JSONObject;
    //   223: aconst_null
    //   224: aconst_null
    //   225: aconst_null
    //   226: aconst_null
    //   227: aload_0
    //   228: getfield 43	com/google/android/gms/internal/ads/aw:c	Lcom/google/android/gms/internal/ads/ik;
    //   231: getfield 47	com/google/android/gms/internal/ads/ik:b	Lcom/google/android/gms/internal/ads/zzaej;
    //   234: getfield 155	com/google/android/gms/internal/ads/zzaej:D	Z
    //   237: aload_0
    //   238: getfield 43	com/google/android/gms/internal/ads/aw:c	Lcom/google/android/gms/internal/ads/ik;
    //   241: getfield 47	com/google/android/gms/internal/ads/ik:b	Lcom/google/android/gms/internal/ads/zzaej;
    //   244: getfield 159	com/google/android/gms/internal/ads/zzaej:E	Lcom/google/android/gms/internal/ads/zzael;
    //   247: aconst_null
    //   248: aconst_null
    //   249: aload_0
    //   250: getfield 48	com/google/android/gms/internal/ads/aw:b	Lcom/google/android/gms/internal/ads/zzaej;
    //   253: getfield 162	com/google/android/gms/internal/ads/zzaej:L	Ljava/lang/String;
    //   256: aload_0
    //   257: getfield 43	com/google/android/gms/internal/ads/aw:c	Lcom/google/android/gms/internal/ads/ik;
    //   260: getfield 165	com/google/android/gms/internal/ads/ik:i	Lcom/google/android/gms/internal/ads/amj;
    //   263: aload_0
    //   264: getfield 43	com/google/android/gms/internal/ads/aw:c	Lcom/google/android/gms/internal/ads/ik;
    //   267: getfield 47	com/google/android/gms/internal/ads/ik:b	Lcom/google/android/gms/internal/ads/zzaej;
    //   270: getfield 168	com/google/android/gms/internal/ads/zzaej:O	Z
    //   273: iconst_0
    //   274: aload_0
    //   275: getfield 43	com/google/android/gms/internal/ads/aw:c	Lcom/google/android/gms/internal/ads/ik;
    //   278: getfield 47	com/google/android/gms/internal/ads/ik:b	Lcom/google/android/gms/internal/ads/zzaej;
    //   281: getfield 171	com/google/android/gms/internal/ads/zzaej:Q	Z
    //   284: aconst_null
    //   285: aload_0
    //   286: getfield 43	com/google/android/gms/internal/ads/aw:c	Lcom/google/android/gms/internal/ads/ik;
    //   289: getfield 47	com/google/android/gms/internal/ads/ik:b	Lcom/google/android/gms/internal/ads/zzaej;
    //   292: getfield 174	com/google/android/gms/internal/ads/zzaej:S	Z
    //   295: aload_0
    //   296: getfield 43	com/google/android/gms/internal/ads/aw:c	Lcom/google/android/gms/internal/ads/ik;
    //   299: getfield 47	com/google/android/gms/internal/ads/ik:b	Lcom/google/android/gms/internal/ads/zzaej;
    //   302: getfield 177	com/google/android/gms/internal/ads/zzaej:T	Ljava/lang/String;
    //   305: invokespecial 180	com/google/android/gms/internal/ads/ij:<init>	(Lcom/google/android/gms/internal/ads/zzjj;Lcom/google/android/gms/internal/ads/qe;Ljava/util/List;ILjava/util/List;Ljava/util/List;IJLjava/lang/String;ZLcom/google/android/gms/internal/ads/bbt;Lcom/google/android/gms/internal/ads/bcn;Ljava/lang/String;Lcom/google/android/gms/internal/ads/bbu;Lcom/google/android/gms/internal/ads/bbx;JLcom/google/android/gms/internal/ads/zzjn;JJJLjava/lang/String;Lorg/json/JSONObject;Lcom/google/android/gms/internal/ads/att;Lcom/google/android/gms/internal/ads/zzaig;Ljava/util/List;Ljava/util/List;ZLcom/google/android/gms/internal/ads/zzael;Ljava/lang/String;Ljava/util/List;Ljava/lang/String;Lcom/google/android/gms/internal/ads/amj;ZZZLjava/util/List;ZLjava/lang/String;)V
    //   308: astore_3
    //   309: goto -260 -> 49
    // Local variable table:
    //   start	length	slot	name	signature
    //   0	312	0	this	aw
    //   2	140	1	i	int
    //   117	1	2	localCancellationException	java.util.concurrent.CancellationException
    //   44	265	3	localij	ij
    //   108	1	5	localInterruptedException	java.lang.InterruptedException
    //   99	1	6	localExecutionException	java.util.concurrent.ExecutionException
    //   74	1	7	localTimeoutException	java.util.concurrent.TimeoutException
    //   66	6	10	localObject2	Object
    // Exception table:
    //   from	to	target	type
    //   12	26	66	finally
    //   68	71	66	finally
    //   3	12	74	java/util/concurrent/TimeoutException
    //   26	45	74	java/util/concurrent/TimeoutException
    //   71	74	74	java/util/concurrent/TimeoutException
    //   3	12	99	java/util/concurrent/ExecutionException
    //   26	45	99	java/util/concurrent/ExecutionException
    //   71	74	99	java/util/concurrent/ExecutionException
    //   3	12	108	java/lang/InterruptedException
    //   26	45	108	java/lang/InterruptedException
    //   71	74	108	java/lang/InterruptedException
    //   3	12	117	java/util/concurrent/CancellationException
    //   26	45	117	java/util/concurrent/CancellationException
    //   71	74	117	java/util/concurrent/CancellationException
  }
  
  public final void b_()
  {
    synchronized (this.e)
    {
      if (this.f != null) {
        this.f.cancel(true);
      }
      return;
    }
  }
}


/* Location:           C:\Users\IrfanRZ\Desktop\video walp\classes_dex2jar.jar
 * Qualified Name:     com.google.android.gms.internal.ads.aw
 * JD-Core Version:    0.7.0.1
 */