package com.google.android.gms.internal.ads;

import java.io.IOException;
import java.io.InputStream;

public class ib
  implements aqr
{
  private static final boolean a = eb.a;
  @Deprecated
  private final qi b;
  private final hc c;
  private final jc d;
  
  public ib(hc paramhc)
  {
    this(paramhc, new jc(4096));
  }
  
  private ib(hc paramhc, jc paramjc)
  {
    this.c = paramhc;
    this.b = paramhc;
    this.d = paramjc;
  }
  
  @Deprecated
  public ib(qi paramqi)
  {
    this(paramqi, new jc(4096));
  }
  
  @Deprecated
  private ib(qi paramqi, jc paramjc)
  {
    this.b = paramqi;
    this.c = new gc(paramqi);
    this.d = paramjc;
  }
  
  private static void a(String paramString, avs<?> paramavs, df paramdf)
  {
    ac localac = paramavs.j();
    int i = paramavs.i();
    try
    {
      localac.a(paramdf);
      Object[] arrayOfObject2 = new Object[2];
      arrayOfObject2[0] = paramString;
      arrayOfObject2[1] = Integer.valueOf(i);
      paramavs.b(String.format("%s-retry [timeout=%s]", arrayOfObject2));
      return;
    }
    catch (df localdf)
    {
      Object[] arrayOfObject1 = new Object[2];
      arrayOfObject1[0] = paramString;
      arrayOfObject1[1] = Integer.valueOf(i);
      paramavs.b(String.format("%s-timeout-giveup [timeout=%s]", arrayOfObject1));
      throw localdf;
    }
  }
  
  private final byte[] a(InputStream paramInputStream, int paramInt)
  {
    th localth = new th(this.d, paramInt);
    byte[] arrayOfByte1 = null;
    if (paramInputStream == null) {
      try
      {
        throw new bd();
      }
      finally
      {
        if (paramInputStream == null) {}
      }
    }
    try
    {
      paramInputStream.close();
      this.d.a(arrayOfByte1);
      localth.close();
      throw localObject;
      arrayOfByte1 = this.d.a(1024);
      for (;;)
      {
        int i = paramInputStream.read(arrayOfByte1);
        if (i == -1) {
          break;
        }
        localth.write(arrayOfByte1, 0, i);
      }
      byte[] arrayOfByte2 = localth.toByteArray();
      if (paramInputStream != null) {}
      try
      {
        paramInputStream.close();
        this.d.a(arrayOfByte1);
        localth.close();
        return arrayOfByte2;
      }
      catch (IOException localIOException2)
      {
        for (;;)
        {
          eb.a("Error occurred when closing InputStream", new Object[0]);
        }
      }
    }
    catch (IOException localIOException1)
    {
      for (;;)
      {
        eb.a("Error occurred when closing InputStream", new Object[0]);
      }
    }
  }
  
  /* Error */
  public atr a(avs<?> paramavs)
  {
    // Byte code:
    //   0: invokestatic 136	android/os/SystemClock:elapsedRealtime	()J
    //   3: lstore_2
    //   4: invokestatic 142	java/util/Collections:emptyList	()Ljava/util/List;
    //   7: astore 4
    //   9: aload_1
    //   10: invokevirtual 146	com/google/android/gms/internal/ads/avs:f	()Lcom/google/android/gms/internal/ads/agn;
    //   13: astore 15
    //   15: aload 15
    //   17: ifnonnull +77 -> 94
    //   20: invokestatic 150	java/util/Collections:emptyMap	()Ljava/util/Map;
    //   23: astore 16
    //   25: aload_0
    //   26: getfield 36	com/google/android/gms/internal/ads/ib:c	Lcom/google/android/gms/internal/ads/hc;
    //   29: aload_1
    //   30: aload 16
    //   32: invokevirtual 155	com/google/android/gms/internal/ads/hc:a	(Lcom/google/android/gms/internal/ads/avs;Ljava/util/Map;)Lcom/google/android/gms/internal/ads/ph;
    //   35: astore 17
    //   37: aload 17
    //   39: invokevirtual 159	com/google/android/gms/internal/ads/ph:a	()I
    //   42: istore 18
    //   44: aload 17
    //   46: invokevirtual 161	com/google/android/gms/internal/ads/ph:b	()Ljava/util/List;
    //   49: astore 4
    //   51: iload 18
    //   53: sipush 304
    //   56: if_icmpne +562 -> 618
    //   59: aload_1
    //   60: invokevirtual 146	com/google/android/gms/internal/ads/avs:f	()Lcom/google/android/gms/internal/ads/agn;
    //   63: astore 19
    //   65: aload 19
    //   67: ifnonnull +108 -> 175
    //   70: new 163	com/google/android/gms/internal/ads/atr
    //   73: dup
    //   74: sipush 304
    //   77: aconst_null
    //   78: iconst_1
    //   79: invokestatic 136	android/os/SystemClock:elapsedRealtime	()J
    //   82: lload_2
    //   83: lsub
    //   84: aload 4
    //   86: invokespecial 166	com/google/android/gms/internal/ads/atr:<init>	(I[BZJLjava/util/List;)V
    //   89: astore 20
    //   91: aload 20
    //   93: areturn
    //   94: new 168	java/util/HashMap
    //   97: dup
    //   98: invokespecial 169	java/util/HashMap:<init>	()V
    //   101: astore 16
    //   103: aload 15
    //   105: getfield 174	com/google/android/gms/internal/ads/agn:b	Ljava/lang/String;
    //   108: ifnull +18 -> 126
    //   111: aload 16
    //   113: ldc 176
    //   115: aload 15
    //   117: getfield 174	com/google/android/gms/internal/ads/agn:b	Ljava/lang/String;
    //   120: invokeinterface 182 3 0
    //   125: pop
    //   126: aload 15
    //   128: getfield 185	com/google/android/gms/internal/ads/agn:d	J
    //   131: lconst_0
    //   132: lcmp
    //   133: ifle -108 -> 25
    //   136: aload 16
    //   138: ldc 187
    //   140: aload 15
    //   142: getfield 185	com/google/android/gms/internal/ads/agn:d	J
    //   145: invokestatic 192	com/google/android/gms/internal/ads/og:a	(J)Ljava/lang/String;
    //   148: invokeinterface 182 3 0
    //   153: pop
    //   154: goto -129 -> 25
    //   157: astore 14
    //   159: ldc 194
    //   161: aload_1
    //   162: new 196	com/google/android/gms/internal/ads/ce
    //   165: dup
    //   166: invokespecial 197	com/google/android/gms/internal/ads/ce:<init>	()V
    //   169: invokestatic 199	com/google/android/gms/internal/ads/ib:a	(Ljava/lang/String;Lcom/google/android/gms/internal/ads/avs;Lcom/google/android/gms/internal/ads/df;)V
    //   172: goto -168 -> 4
    //   175: new 201	java/util/TreeSet
    //   178: dup
    //   179: getstatic 205	java/lang/String:CASE_INSENSITIVE_ORDER	Ljava/util/Comparator;
    //   182: invokespecial 208	java/util/TreeSet:<init>	(Ljava/util/Comparator;)V
    //   185: astore 21
    //   187: aload 4
    //   189: invokeinterface 214 1 0
    //   194: ifne +86 -> 280
    //   197: aload 4
    //   199: invokeinterface 218 1 0
    //   204: astore 29
    //   206: aload 29
    //   208: invokeinterface 223 1 0
    //   213: ifeq +67 -> 280
    //   216: aload 21
    //   218: aload 29
    //   220: invokeinterface 227 1 0
    //   225: checkcast 229	com/google/android/gms/internal/ads/apr
    //   228: invokevirtual 232	com/google/android/gms/internal/ads/apr:a	()Ljava/lang/String;
    //   231: invokeinterface 238 2 0
    //   236: pop
    //   237: goto -31 -> 206
    //   240: astore 11
    //   242: aload_1
    //   243: invokevirtual 241	com/google/android/gms/internal/ads/avs:e	()Ljava/lang/String;
    //   246: invokestatic 244	java/lang/String:valueOf	(Ljava/lang/Object;)Ljava/lang/String;
    //   249: astore 12
    //   251: aload 12
    //   253: invokevirtual 247	java/lang/String:length	()I
    //   256: ifeq +545 -> 801
    //   259: ldc 249
    //   261: aload 12
    //   263: invokevirtual 253	java/lang/String:concat	(Ljava/lang/String;)Ljava/lang/String;
    //   266: astore 13
    //   268: new 255	java/lang/RuntimeException
    //   271: dup
    //   272: aload 13
    //   274: aload 11
    //   276: invokespecial 258	java/lang/RuntimeException:<init>	(Ljava/lang/String;Ljava/lang/Throwable;)V
    //   279: athrow
    //   280: new 260	java/util/ArrayList
    //   283: dup
    //   284: aload 4
    //   286: invokespecial 263	java/util/ArrayList:<init>	(Ljava/util/Collection;)V
    //   289: astore 22
    //   291: aload 19
    //   293: getfield 267	com/google/android/gms/internal/ads/agn:h	Ljava/util/List;
    //   296: ifnull +191 -> 487
    //   299: aload 19
    //   301: getfield 267	com/google/android/gms/internal/ads/agn:h	Ljava/util/List;
    //   304: invokeinterface 214 1 0
    //   309: ifne +285 -> 594
    //   312: aload 19
    //   314: getfield 267	com/google/android/gms/internal/ads/agn:h	Ljava/util/List;
    //   317: invokeinterface 218 1 0
    //   322: astore 26
    //   324: aload 26
    //   326: invokeinterface 223 1 0
    //   331: ifeq +263 -> 594
    //   334: aload 26
    //   336: invokeinterface 227 1 0
    //   341: checkcast 229	com/google/android/gms/internal/ads/apr
    //   344: astore 27
    //   346: aload 21
    //   348: aload 27
    //   350: invokevirtual 232	com/google/android/gms/internal/ads/apr:a	()Ljava/lang/String;
    //   353: invokeinterface 270 2 0
    //   358: ifne -34 -> 324
    //   361: aload 22
    //   363: aload 27
    //   365: invokeinterface 271 2 0
    //   370: pop
    //   371: goto -47 -> 324
    //   374: astore 5
    //   376: aconst_null
    //   377: astore 7
    //   379: aload 17
    //   381: astore 6
    //   383: aload 6
    //   385: ifnull +430 -> 815
    //   388: aload 6
    //   390: invokevirtual 159	com/google/android/gms/internal/ads/ph:a	()I
    //   393: istore 8
    //   395: iconst_2
    //   396: anewarray 4	java/lang/Object
    //   399: astore 9
    //   401: aload 9
    //   403: iconst_0
    //   404: iload 8
    //   406: invokestatic 72	java/lang/Integer:valueOf	(I)Ljava/lang/Integer;
    //   409: aastore
    //   410: aload 9
    //   412: iconst_1
    //   413: aload_1
    //   414: invokevirtual 241	com/google/android/gms/internal/ads/avs:e	()Ljava/lang/String;
    //   417: aastore
    //   418: ldc_w 273
    //   421: aload 9
    //   423: invokestatic 275	com/google/android/gms/internal/ads/eb:c	(Ljava/lang/String;[Ljava/lang/Object;)V
    //   426: aload 7
    //   428: ifnull +459 -> 887
    //   431: new 163	com/google/android/gms/internal/ads/atr
    //   434: dup
    //   435: iload 8
    //   437: aload 7
    //   439: iconst_0
    //   440: invokestatic 136	android/os/SystemClock:elapsedRealtime	()J
    //   443: lload_2
    //   444: lsub
    //   445: aload 4
    //   447: invokespecial 166	com/google/android/gms/internal/ads/atr:<init>	(I[BZJLjava/util/List;)V
    //   450: astore 10
    //   452: iload 8
    //   454: sipush 401
    //   457: if_icmpeq +11 -> 468
    //   460: iload 8
    //   462: sipush 403
    //   465: if_icmpne +360 -> 825
    //   468: ldc_w 277
    //   471: aload_1
    //   472: new 279	com/google/android/gms/internal/ads/a
    //   475: dup
    //   476: aload 10
    //   478: invokespecial 282	com/google/android/gms/internal/ads/a:<init>	(Lcom/google/android/gms/internal/ads/atr;)V
    //   481: invokestatic 199	com/google/android/gms/internal/ads/ib:a	(Ljava/lang/String;Lcom/google/android/gms/internal/ads/avs;Lcom/google/android/gms/internal/ads/df;)V
    //   484: goto -480 -> 4
    //   487: aload 19
    //   489: getfield 286	com/google/android/gms/internal/ads/agn:g	Ljava/util/Map;
    //   492: invokeinterface 287 1 0
    //   497: ifne +97 -> 594
    //   500: aload 19
    //   502: getfield 286	com/google/android/gms/internal/ads/agn:g	Ljava/util/Map;
    //   505: invokeinterface 291 1 0
    //   510: invokeinterface 292 1 0
    //   515: astore 23
    //   517: aload 23
    //   519: invokeinterface 223 1 0
    //   524: ifeq +70 -> 594
    //   527: aload 23
    //   529: invokeinterface 227 1 0
    //   534: checkcast 294	java/util/Map$Entry
    //   537: astore 24
    //   539: aload 21
    //   541: aload 24
    //   543: invokeinterface 297 1 0
    //   548: invokeinterface 270 2 0
    //   553: ifne -36 -> 517
    //   556: aload 22
    //   558: new 229	com/google/android/gms/internal/ads/apr
    //   561: dup
    //   562: aload 24
    //   564: invokeinterface 297 1 0
    //   569: checkcast 76	java/lang/String
    //   572: aload 24
    //   574: invokeinterface 300 1 0
    //   579: checkcast 76	java/lang/String
    //   582: invokespecial 303	com/google/android/gms/internal/ads/apr:<init>	(Ljava/lang/String;Ljava/lang/String;)V
    //   585: invokeinterface 271 2 0
    //   590: pop
    //   591: goto -74 -> 517
    //   594: new 163	com/google/android/gms/internal/ads/atr
    //   597: dup
    //   598: sipush 304
    //   601: aload 19
    //   603: getfield 306	com/google/android/gms/internal/ads/agn:a	[B
    //   606: iconst_1
    //   607: invokestatic 136	android/os/SystemClock:elapsedRealtime	()J
    //   610: lload_2
    //   611: lsub
    //   612: aload 22
    //   614: invokespecial 166	com/google/android/gms/internal/ads/atr:<init>	(I[BZJLjava/util/List;)V
    //   617: areturn
    //   618: aload 17
    //   620: invokevirtual 309	com/google/android/gms/internal/ads/ph:d	()Ljava/io/InputStream;
    //   623: astore 31
    //   625: aload 31
    //   627: ifnull +134 -> 761
    //   630: aload_0
    //   631: aload 31
    //   633: aload 17
    //   635: invokevirtual 311	com/google/android/gms/internal/ads/ph:c	()I
    //   638: invokespecial 313	com/google/android/gms/internal/ads/ib:a	(Ljava/io/InputStream;I)[B
    //   641: astore 32
    //   643: aload 32
    //   645: astore 7
    //   647: invokestatic 136	android/os/SystemClock:elapsedRealtime	()J
    //   650: lload_2
    //   651: lsub
    //   652: lstore 33
    //   654: getstatic 22	com/google/android/gms/internal/ads/ib:a	Z
    //   657: ifne +12 -> 669
    //   660: lload 33
    //   662: ldc2_w 314
    //   665: lcmp
    //   666: ifle +249 -> 915
    //   669: iconst_5
    //   670: anewarray 4	java/lang/Object
    //   673: astore 36
    //   675: aload 36
    //   677: iconst_0
    //   678: aload_1
    //   679: aastore
    //   680: aload 36
    //   682: iconst_1
    //   683: lload 33
    //   685: invokestatic 320	java/lang/Long:valueOf	(J)Ljava/lang/Long;
    //   688: aastore
    //   689: aload 7
    //   691: ifnull +78 -> 769
    //   694: aload 7
    //   696: arraylength
    //   697: invokestatic 72	java/lang/Integer:valueOf	(I)Ljava/lang/Integer;
    //   700: astore 37
    //   702: aload 36
    //   704: iconst_2
    //   705: aload 37
    //   707: aastore
    //   708: aload 36
    //   710: iconst_3
    //   711: iload 18
    //   713: invokestatic 72	java/lang/Integer:valueOf	(I)Ljava/lang/Integer;
    //   716: aastore
    //   717: aload 36
    //   719: iconst_4
    //   720: aload_1
    //   721: invokevirtual 57	com/google/android/gms/internal/ads/avs:j	()Lcom/google/android/gms/internal/ads/ac;
    //   724: invokeinterface 322 1 0
    //   729: invokestatic 72	java/lang/Integer:valueOf	(I)Ljava/lang/Integer;
    //   732: aastore
    //   733: ldc_w 324
    //   736: aload 36
    //   738: invokestatic 326	com/google/android/gms/internal/ads/eb:b	(Ljava/lang/String;[Ljava/lang/Object;)V
    //   741: goto +174 -> 915
    //   744: new 88	java/io/IOException
    //   747: dup
    //   748: invokespecial 327	java/io/IOException:<init>	()V
    //   751: athrow
    //   752: astore 5
    //   754: aload 17
    //   756: astore 6
    //   758: goto -375 -> 383
    //   761: iconst_0
    //   762: newarray byte
    //   764: astore 7
    //   766: goto -119 -> 647
    //   769: ldc_w 329
    //   772: astore 37
    //   774: goto -72 -> 702
    //   777: new 163	com/google/android/gms/internal/ads/atr
    //   780: dup
    //   781: iload 18
    //   783: aload 7
    //   785: iconst_0
    //   786: invokestatic 136	android/os/SystemClock:elapsedRealtime	()J
    //   789: lload_2
    //   790: lsub
    //   791: aload 4
    //   793: invokespecial 166	com/google/android/gms/internal/ads/atr:<init>	(I[BZJLjava/util/List;)V
    //   796: astore 35
    //   798: aload 35
    //   800: areturn
    //   801: new 76	java/lang/String
    //   804: dup
    //   805: ldc 249
    //   807: invokespecial 331	java/lang/String:<init>	(Ljava/lang/String;)V
    //   810: astore 13
    //   812: goto -544 -> 268
    //   815: new 333	com/google/android/gms/internal/ads/aur
    //   818: dup
    //   819: aload 5
    //   821: invokespecial 336	com/google/android/gms/internal/ads/aur:<init>	(Ljava/lang/Throwable;)V
    //   824: athrow
    //   825: iload 8
    //   827: sipush 400
    //   830: if_icmplt +21 -> 851
    //   833: iload 8
    //   835: sipush 499
    //   838: if_icmpgt +13 -> 851
    //   841: new 338	com/google/android/gms/internal/ads/akr
    //   844: dup
    //   845: aload 10
    //   847: invokespecial 339	com/google/android/gms/internal/ads/akr:<init>	(Lcom/google/android/gms/internal/ads/atr;)V
    //   850: athrow
    //   851: iload 8
    //   853: sipush 500
    //   856: if_icmplt +21 -> 877
    //   859: iload 8
    //   861: sipush 599
    //   864: if_icmpgt +13 -> 877
    //   867: new 95	com/google/android/gms/internal/ads/bd
    //   870: dup
    //   871: aload 10
    //   873: invokespecial 340	com/google/android/gms/internal/ads/bd:<init>	(Lcom/google/android/gms/internal/ads/atr;)V
    //   876: athrow
    //   877: new 95	com/google/android/gms/internal/ads/bd
    //   880: dup
    //   881: aload 10
    //   883: invokespecial 340	com/google/android/gms/internal/ads/bd:<init>	(Lcom/google/android/gms/internal/ads/atr;)V
    //   886: athrow
    //   887: ldc_w 342
    //   890: aload_1
    //   891: new 344	com/google/android/gms/internal/ads/asq
    //   894: dup
    //   895: invokespecial 345	com/google/android/gms/internal/ads/asq:<init>	()V
    //   898: invokestatic 199	com/google/android/gms/internal/ads/ib:a	(Ljava/lang/String;Lcom/google/android/gms/internal/ads/avs;Lcom/google/android/gms/internal/ads/df;)V
    //   901: goto -897 -> 4
    //   904: astore 5
    //   906: aconst_null
    //   907: astore 6
    //   909: aconst_null
    //   910: astore 7
    //   912: goto -529 -> 383
    //   915: iload 18
    //   917: sipush 200
    //   920: if_icmplt -176 -> 744
    //   923: iload 18
    //   925: sipush 299
    //   928: if_icmple -151 -> 777
    //   931: goto -187 -> 744
    // Local variable table:
    //   start	length	slot	name	signature
    //   0	934	0	this	ib
    //   0	934	1	paramavs	avs<?>
    //   3	787	2	l1	long
    //   7	785	4	localList	java.util.List
    //   374	1	5	localIOException1	IOException
    //   752	68	5	localIOException2	IOException
    //   904	1	5	localIOException3	IOException
    //   381	527	6	localph1	ph
    //   377	534	7	localObject1	Object
    //   393	472	8	i	int
    //   399	23	9	arrayOfObject1	Object[]
    //   450	432	10	localatr1	atr
    //   240	35	11	localMalformedURLException	java.net.MalformedURLException
    //   249	13	12	str1	String
    //   266	545	13	str2	String
    //   157	1	14	localSocketTimeoutException	java.net.SocketTimeoutException
    //   13	128	15	localagn1	agn
    //   23	114	16	localObject2	Object
    //   35	720	17	localph2	ph
    //   42	887	18	j	int
    //   63	539	19	localagn2	agn
    //   89	3	20	localatr2	atr
    //   185	355	21	localTreeSet	java.util.TreeSet
    //   289	324	22	localArrayList	java.util.ArrayList
    //   515	13	23	localIterator1	java.util.Iterator
    //   537	36	24	localEntry	java.util.Map.Entry
    //   322	13	26	localIterator2	java.util.Iterator
    //   344	20	27	localapr	apr
    //   204	15	29	localIterator3	java.util.Iterator
    //   623	9	31	localInputStream	InputStream
    //   641	3	32	arrayOfByte	byte[]
    //   652	32	33	l2	long
    //   796	3	35	localatr3	atr
    //   673	64	36	arrayOfObject2	Object[]
    //   700	73	37	localObject3	Object
    // Exception table:
    //   from	to	target	type
    //   9	15	157	java/net/SocketTimeoutException
    //   20	25	157	java/net/SocketTimeoutException
    //   25	37	157	java/net/SocketTimeoutException
    //   37	51	157	java/net/SocketTimeoutException
    //   59	65	157	java/net/SocketTimeoutException
    //   70	91	157	java/net/SocketTimeoutException
    //   94	126	157	java/net/SocketTimeoutException
    //   126	154	157	java/net/SocketTimeoutException
    //   175	206	157	java/net/SocketTimeoutException
    //   206	237	157	java/net/SocketTimeoutException
    //   280	324	157	java/net/SocketTimeoutException
    //   324	371	157	java/net/SocketTimeoutException
    //   487	517	157	java/net/SocketTimeoutException
    //   517	591	157	java/net/SocketTimeoutException
    //   594	618	157	java/net/SocketTimeoutException
    //   618	625	157	java/net/SocketTimeoutException
    //   630	643	157	java/net/SocketTimeoutException
    //   647	660	157	java/net/SocketTimeoutException
    //   669	689	157	java/net/SocketTimeoutException
    //   694	702	157	java/net/SocketTimeoutException
    //   702	741	157	java/net/SocketTimeoutException
    //   744	752	157	java/net/SocketTimeoutException
    //   761	766	157	java/net/SocketTimeoutException
    //   777	798	157	java/net/SocketTimeoutException
    //   9	15	240	java/net/MalformedURLException
    //   20	25	240	java/net/MalformedURLException
    //   25	37	240	java/net/MalformedURLException
    //   37	51	240	java/net/MalformedURLException
    //   59	65	240	java/net/MalformedURLException
    //   70	91	240	java/net/MalformedURLException
    //   94	126	240	java/net/MalformedURLException
    //   126	154	240	java/net/MalformedURLException
    //   175	206	240	java/net/MalformedURLException
    //   206	237	240	java/net/MalformedURLException
    //   280	324	240	java/net/MalformedURLException
    //   324	371	240	java/net/MalformedURLException
    //   487	517	240	java/net/MalformedURLException
    //   517	591	240	java/net/MalformedURLException
    //   594	618	240	java/net/MalformedURLException
    //   618	625	240	java/net/MalformedURLException
    //   630	643	240	java/net/MalformedURLException
    //   647	660	240	java/net/MalformedURLException
    //   669	689	240	java/net/MalformedURLException
    //   694	702	240	java/net/MalformedURLException
    //   702	741	240	java/net/MalformedURLException
    //   744	752	240	java/net/MalformedURLException
    //   761	766	240	java/net/MalformedURLException
    //   777	798	240	java/net/MalformedURLException
    //   37	51	374	java/io/IOException
    //   59	65	374	java/io/IOException
    //   70	91	374	java/io/IOException
    //   175	206	374	java/io/IOException
    //   206	237	374	java/io/IOException
    //   280	324	374	java/io/IOException
    //   324	371	374	java/io/IOException
    //   487	517	374	java/io/IOException
    //   517	591	374	java/io/IOException
    //   594	618	374	java/io/IOException
    //   618	625	374	java/io/IOException
    //   630	643	374	java/io/IOException
    //   761	766	374	java/io/IOException
    //   647	660	752	java/io/IOException
    //   669	689	752	java/io/IOException
    //   694	702	752	java/io/IOException
    //   702	741	752	java/io/IOException
    //   744	752	752	java/io/IOException
    //   777	798	752	java/io/IOException
    //   9	15	904	java/io/IOException
    //   20	25	904	java/io/IOException
    //   25	37	904	java/io/IOException
    //   94	126	904	java/io/IOException
    //   126	154	904	java/io/IOException
  }
}


/* Location:           C:\Users\IrfanRZ\Desktop\video walp\classes_dex2jar.jar
 * Qualified Name:     com.google.android.gms.internal.ads.ib
 * JD-Core Version:    0.7.0.1
 */