package com.google.android.gms.internal.ads;

import android.content.Context;
import java.io.File;
import java.text.DecimalFormat;
import java.util.Collections;
import java.util.HashSet;
import java.util.Set;

@cm
public final class pv
  extends pp
{
  private static final Set<String> b = Collections.synchronizedSet(new HashSet());
  private static final DecimalFormat c = new DecimalFormat("#,###");
  private File d;
  private boolean e;
  
  public pv(pd parampd)
  {
    super(parampd);
    File localFile = this.a.getCacheDir();
    if (localFile == null) {
      je.e("Context.getCacheDir() returned null");
    }
    do
    {
      return;
      this.d = new File(localFile, "admobVideoStreams");
      if ((!this.d.isDirectory()) && (!this.d.mkdirs()))
      {
        String str3 = String.valueOf(this.d.getAbsolutePath());
        if (str3.length() != 0) {}
        for (String str4 = "Could not create preload cache directory at ".concat(str3);; str4 = new String("Could not create preload cache directory at "))
        {
          je.e(str4);
          this.d = null;
          return;
        }
      }
    } while ((this.d.setReadable(true, false)) && (this.d.setExecutable(true, false)));
    String str1 = String.valueOf(this.d.getAbsolutePath());
    if (str1.length() != 0) {}
    for (String str2 = "Could not set cache file permissions at ".concat(str1);; str2 = new String("Could not set cache file permissions at "))
    {
      je.e(str2);
      this.d = null;
      return;
    }
  }
  
  private final File a(File paramFile)
  {
    return new File(this.d, String.valueOf(paramFile.getName()).concat(".done"));
  }
  
  public final void a()
  {
    this.e = true;
  }
  
  /* Error */
  public final boolean a(String paramString)
  {
    // Byte code:
    //   0: aload_0
    //   1: getfield 66	com/google/android/gms/internal/ads/pv:d	Ljava/io/File;
    //   4: ifnonnull +14 -> 18
    //   7: aload_0
    //   8: aload_1
    //   9: aconst_null
    //   10: ldc 120
    //   12: aconst_null
    //   13: invokevirtual 123	com/google/android/gms/internal/ads/pp:a	(Ljava/lang/String;Ljava/lang/String;Ljava/lang/String;Ljava/lang/String;)V
    //   16: iconst_0
    //   17: ireturn
    //   18: aload_0
    //   19: getfield 66	com/google/android/gms/internal/ads/pv:d	Ljava/io/File;
    //   22: ifnonnull +61 -> 83
    //   25: iconst_0
    //   26: istore 6
    //   28: getstatic 129	com/google/android/gms/internal/ads/asa:n	Lcom/google/android/gms/internal/ads/arq;
    //   31: astore 7
    //   33: iload 6
    //   35: invokestatic 135	com/google/android/gms/internal/ads/aos:f	()Lcom/google/android/gms/internal/ads/ary;
    //   38: aload 7
    //   40: invokevirtual 140	com/google/android/gms/internal/ads/ary:a	(Lcom/google/android/gms/internal/ads/arq;)Ljava/lang/Object;
    //   43: checkcast 142	java/lang/Integer
    //   46: invokevirtual 145	java/lang/Integer:intValue	()I
    //   49: if_icmple +217 -> 266
    //   52: aload_0
    //   53: getfield 66	com/google/android/gms/internal/ads/pv:d	Ljava/io/File;
    //   56: ifnonnull +81 -> 137
    //   59: iconst_0
    //   60: istore 98
    //   62: iload 98
    //   64: ifne -46 -> 18
    //   67: ldc 147
    //   69: invokestatic 57	com/google/android/gms/internal/ads/je:e	(Ljava/lang/String;)V
    //   72: aload_0
    //   73: aload_1
    //   74: aconst_null
    //   75: ldc 149
    //   77: aconst_null
    //   78: invokevirtual 123	com/google/android/gms/internal/ads/pp:a	(Ljava/lang/String;Ljava/lang/String;Ljava/lang/String;Ljava/lang/String;)V
    //   81: iconst_0
    //   82: ireturn
    //   83: aload_0
    //   84: getfield 66	com/google/android/gms/internal/ads/pv:d	Ljava/io/File;
    //   87: invokevirtual 153	java/io/File:listFiles	()[Ljava/io/File;
    //   90: astore_2
    //   91: aload_2
    //   92: arraylength
    //   93: istore_3
    //   94: iconst_0
    //   95: istore 4
    //   97: iconst_0
    //   98: istore 5
    //   100: iload 5
    //   102: iload_3
    //   103: if_icmpge +27 -> 130
    //   106: aload_2
    //   107: iload 5
    //   109: aaload
    //   110: invokevirtual 107	java/io/File:getName	()Ljava/lang/String;
    //   113: ldc 109
    //   115: invokevirtual 156	java/lang/String:endsWith	(Ljava/lang/String;)Z
    //   118: ifne +6 -> 124
    //   121: iinc 4 1
    //   124: iinc 5 1
    //   127: goto -27 -> 100
    //   130: iload 4
    //   132: istore 6
    //   134: goto -106 -> 28
    //   137: aconst_null
    //   138: astore 92
    //   140: ldc2_w 157
    //   143: lstore 93
    //   145: aload_0
    //   146: getfield 66	com/google/android/gms/internal/ads/pv:d	Ljava/io/File;
    //   149: invokevirtual 153	java/io/File:listFiles	()[Ljava/io/File;
    //   152: astore 95
    //   154: aload 95
    //   156: arraylength
    //   157: istore 96
    //   159: iconst_0
    //   160: istore 97
    //   162: iload 97
    //   164: iload 96
    //   166: if_icmpge +56 -> 222
    //   169: aload 95
    //   171: iload 97
    //   173: aaload
    //   174: astore 100
    //   176: aload 100
    //   178: invokevirtual 107	java/io/File:getName	()Ljava/lang/String;
    //   181: ldc 109
    //   183: invokevirtual 156	java/lang/String:endsWith	(Ljava/lang/String;)Z
    //   186: ifne +1952 -> 2138
    //   189: aload 100
    //   191: invokevirtual 162	java/io/File:lastModified	()J
    //   194: lstore 101
    //   196: lload 101
    //   198: lload 93
    //   200: lcmp
    //   201: ifge +1937 -> 2138
    //   204: aload 100
    //   206: astore 103
    //   208: iinc 97 1
    //   211: aload 103
    //   213: astore 92
    //   215: lload 101
    //   217: lstore 93
    //   219: goto -57 -> 162
    //   222: iconst_0
    //   223: istore 98
    //   225: aload 92
    //   227: ifnull -165 -> 62
    //   230: aload 92
    //   232: invokevirtual 165	java/io/File:delete	()Z
    //   235: istore 98
    //   237: aload_0
    //   238: aload 92
    //   240: invokespecial 167	com/google/android/gms/internal/ads/pv:a	(Ljava/io/File;)Ljava/io/File;
    //   243: astore 99
    //   245: aload 99
    //   247: invokevirtual 170	java/io/File:isFile	()Z
    //   250: ifeq -188 -> 62
    //   253: iload 98
    //   255: aload 99
    //   257: invokevirtual 165	java/io/File:delete	()Z
    //   260: iand
    //   261: istore 98
    //   263: goto -201 -> 62
    //   266: invokestatic 173	com/google/android/gms/internal/ads/aos:a	()Lcom/google/android/gms/internal/ads/lz;
    //   269: pop
    //   270: aload_1
    //   271: invokestatic 177	com/google/android/gms/internal/ads/lz:a	(Ljava/lang/String;)Ljava/lang/String;
    //   274: astore 9
    //   276: new 59	java/io/File
    //   279: dup
    //   280: aload_0
    //   281: getfield 66	com/google/android/gms/internal/ads/pv:d	Ljava/io/File;
    //   284: aload 9
    //   286: invokespecial 64	java/io/File:<init>	(Ljava/io/File;Ljava/lang/String;)V
    //   289: astore 10
    //   291: aload_0
    //   292: aload 10
    //   294: invokespecial 167	com/google/android/gms/internal/ads/pv:a	(Ljava/io/File;)Ljava/io/File;
    //   297: astore 11
    //   299: aload 10
    //   301: invokevirtual 170	java/io/File:isFile	()Z
    //   304: ifeq +75 -> 379
    //   307: aload 11
    //   309: invokevirtual 170	java/io/File:isFile	()Z
    //   312: ifeq +67 -> 379
    //   315: aload 10
    //   317: invokevirtual 179	java/io/File:length	()J
    //   320: l2i
    //   321: istore 89
    //   323: aload_1
    //   324: invokestatic 83	java/lang/String:valueOf	(Ljava/lang/Object;)Ljava/lang/String;
    //   327: astore 90
    //   329: aload 90
    //   331: invokevirtual 87	java/lang/String:length	()I
    //   334: ifeq +31 -> 365
    //   337: ldc 181
    //   339: aload 90
    //   341: invokevirtual 93	java/lang/String:concat	(Ljava/lang/String;)Ljava/lang/String;
    //   344: astore 91
    //   346: aload 91
    //   348: invokestatic 183	com/google/android/gms/internal/ads/je:b	(Ljava/lang/String;)V
    //   351: aload_0
    //   352: aload_1
    //   353: aload 10
    //   355: invokevirtual 77	java/io/File:getAbsolutePath	()Ljava/lang/String;
    //   358: iload 89
    //   360: invokevirtual 186	com/google/android/gms/internal/ads/pp:a	(Ljava/lang/String;Ljava/lang/String;I)V
    //   363: iconst_1
    //   364: ireturn
    //   365: new 79	java/lang/String
    //   368: dup
    //   369: ldc 181
    //   371: invokespecial 94	java/lang/String:<init>	(Ljava/lang/String;)V
    //   374: astore 91
    //   376: goto -30 -> 346
    //   379: aload_0
    //   380: getfield 66	com/google/android/gms/internal/ads/pv:d	Ljava/io/File;
    //   383: invokevirtual 77	java/io/File:getAbsolutePath	()Ljava/lang/String;
    //   386: invokestatic 83	java/lang/String:valueOf	(Ljava/lang/Object;)Ljava/lang/String;
    //   389: astore 12
    //   391: aload_1
    //   392: invokestatic 83	java/lang/String:valueOf	(Ljava/lang/Object;)Ljava/lang/String;
    //   395: astore 13
    //   397: aload 13
    //   399: invokevirtual 87	java/lang/String:length	()I
    //   402: ifeq +87 -> 489
    //   405: aload 12
    //   407: aload 13
    //   409: invokevirtual 93	java/lang/String:concat	(Ljava/lang/String;)Ljava/lang/String;
    //   412: astore 14
    //   414: getstatic 29	com/google/android/gms/internal/ads/pv:b	Ljava/util/Set;
    //   417: astore 15
    //   419: aload 15
    //   421: monitorenter
    //   422: getstatic 29	com/google/android/gms/internal/ads/pv:b	Ljava/util/Set;
    //   425: aload 14
    //   427: invokeinterface 192 2 0
    //   432: ifeq +85 -> 517
    //   435: aload_1
    //   436: invokestatic 83	java/lang/String:valueOf	(Ljava/lang/Object;)Ljava/lang/String;
    //   439: astore 87
    //   441: aload 87
    //   443: invokevirtual 87	java/lang/String:length	()I
    //   446: ifeq +57 -> 503
    //   449: ldc 194
    //   451: aload 87
    //   453: invokevirtual 93	java/lang/String:concat	(Ljava/lang/String;)Ljava/lang/String;
    //   456: astore 88
    //   458: aload 88
    //   460: invokestatic 57	com/google/android/gms/internal/ads/je:e	(Ljava/lang/String;)V
    //   463: aload_0
    //   464: aload_1
    //   465: aload 10
    //   467: invokevirtual 77	java/io/File:getAbsolutePath	()Ljava/lang/String;
    //   470: ldc 196
    //   472: aconst_null
    //   473: invokevirtual 123	com/google/android/gms/internal/ads/pp:a	(Ljava/lang/String;Ljava/lang/String;Ljava/lang/String;Ljava/lang/String;)V
    //   476: aload 15
    //   478: monitorexit
    //   479: iconst_0
    //   480: ireturn
    //   481: astore 16
    //   483: aload 15
    //   485: monitorexit
    //   486: aload 16
    //   488: athrow
    //   489: new 79	java/lang/String
    //   492: dup
    //   493: aload 12
    //   495: invokespecial 94	java/lang/String:<init>	(Ljava/lang/String;)V
    //   498: astore 14
    //   500: goto -86 -> 414
    //   503: new 79	java/lang/String
    //   506: dup
    //   507: ldc 194
    //   509: invokespecial 94	java/lang/String:<init>	(Ljava/lang/String;)V
    //   512: astore 88
    //   514: goto -56 -> 458
    //   517: getstatic 29	com/google/android/gms/internal/ads/pv:b	Ljava/util/Set;
    //   520: aload 14
    //   522: invokeinterface 199 2 0
    //   527: pop
    //   528: aload 15
    //   530: monitorexit
    //   531: aconst_null
    //   532: astore 18
    //   534: invokestatic 205	com/google/android/gms/ads/internal/zzbv:zzew	()Lcom/google/android/gms/internal/ads/nq;
    //   537: pop
    //   538: getstatic 208	com/google/android/gms/internal/ads/asa:s	Lcom/google/android/gms/internal/ads/arq;
    //   541: astore 28
    //   543: invokestatic 135	com/google/android/gms/internal/ads/aos:f	()Lcom/google/android/gms/internal/ads/ary;
    //   546: aload 28
    //   548: invokevirtual 140	com/google/android/gms/internal/ads/ary:a	(Lcom/google/android/gms/internal/ads/arq;)Ljava/lang/Object;
    //   551: checkcast 142	java/lang/Integer
    //   554: invokevirtual 145	java/lang/Integer:intValue	()I
    //   557: istore 29
    //   559: new 210	java/net/URL
    //   562: dup
    //   563: aload_1
    //   564: invokespecial 211	java/net/URL:<init>	(Ljava/lang/String;)V
    //   567: astore 30
    //   569: iconst_0
    //   570: istore 31
    //   572: iload 31
    //   574: iconst_1
    //   575: iadd
    //   576: istore 32
    //   578: iload 32
    //   580: bipush 20
    //   582: if_icmpgt +445 -> 1027
    //   585: aload 30
    //   587: invokevirtual 215	java/net/URL:openConnection	()Ljava/net/URLConnection;
    //   590: astore 33
    //   592: aload 33
    //   594: iload 29
    //   596: invokevirtual 221	java/net/URLConnection:setConnectTimeout	(I)V
    //   599: aload 33
    //   601: iload 29
    //   603: invokevirtual 224	java/net/URLConnection:setReadTimeout	(I)V
    //   606: aload 33
    //   608: instanceof 226
    //   611: ifne +166 -> 777
    //   614: new 114	java/io/IOException
    //   617: dup
    //   618: ldc 228
    //   620: invokespecial 229	java/io/IOException:<init>	(Ljava/lang/String;)V
    //   623: athrow
    //   624: astore 19
    //   626: aconst_null
    //   627: astore 21
    //   629: ldc 231
    //   631: astore 20
    //   633: aload 19
    //   635: instanceof 116
    //   638: ifeq +13 -> 651
    //   641: invokestatic 235	com/google/android/gms/ads/internal/zzbv:zzeo	()Lcom/google/android/gms/internal/ads/io;
    //   644: aload 19
    //   646: ldc 237
    //   648: invokevirtual 242	com/google/android/gms/internal/ads/io:a	(Ljava/lang/Throwable;Ljava/lang/String;)V
    //   651: aload 18
    //   653: invokevirtual 247	java/io/FileOutputStream:close	()V
    //   656: aload_0
    //   657: getfield 111	com/google/android/gms/internal/ads/pv:e	Z
    //   660: ifeq +1374 -> 2034
    //   663: new 249	java/lang/StringBuilder
    //   666: dup
    //   667: bipush 26
    //   669: aload_1
    //   670: invokestatic 83	java/lang/String:valueOf	(Ljava/lang/Object;)Ljava/lang/String;
    //   673: invokevirtual 87	java/lang/String:length	()I
    //   676: iadd
    //   677: invokespecial 251	java/lang/StringBuilder:<init>	(I)V
    //   680: ldc 253
    //   682: invokevirtual 257	java/lang/StringBuilder:append	(Ljava/lang/String;)Ljava/lang/StringBuilder;
    //   685: aload_1
    //   686: invokevirtual 257	java/lang/StringBuilder:append	(Ljava/lang/String;)Ljava/lang/StringBuilder;
    //   689: ldc_w 259
    //   692: invokevirtual 257	java/lang/StringBuilder:append	(Ljava/lang/String;)Ljava/lang/StringBuilder;
    //   695: invokevirtual 262	java/lang/StringBuilder:toString	()Ljava/lang/String;
    //   698: invokestatic 264	com/google/android/gms/internal/ads/je:d	(Ljava/lang/String;)V
    //   701: aload 10
    //   703: invokevirtual 267	java/io/File:exists	()Z
    //   706: ifeq +44 -> 750
    //   709: aload 10
    //   711: invokevirtual 165	java/io/File:delete	()Z
    //   714: ifne +36 -> 750
    //   717: aload 10
    //   719: invokevirtual 77	java/io/File:getAbsolutePath	()Ljava/lang/String;
    //   722: invokestatic 83	java/lang/String:valueOf	(Ljava/lang/Object;)Ljava/lang/String;
    //   725: astore 24
    //   727: aload 24
    //   729: invokevirtual 87	java/lang/String:length	()I
    //   732: ifeq +1346 -> 2078
    //   735: ldc_w 269
    //   738: aload 24
    //   740: invokevirtual 93	java/lang/String:concat	(Ljava/lang/String;)Ljava/lang/String;
    //   743: astore 25
    //   745: aload 25
    //   747: invokestatic 57	com/google/android/gms/internal/ads/je:e	(Ljava/lang/String;)V
    //   750: aload_0
    //   751: aload_1
    //   752: aload 10
    //   754: invokevirtual 77	java/io/File:getAbsolutePath	()Ljava/lang/String;
    //   757: aload 20
    //   759: aload 21
    //   761: invokevirtual 123	com/google/android/gms/internal/ads/pp:a	(Ljava/lang/String;Ljava/lang/String;Ljava/lang/String;Ljava/lang/String;)V
    //   764: getstatic 29	com/google/android/gms/internal/ads/pv:b	Ljava/util/Set;
    //   767: aload 14
    //   769: invokeinterface 272 2 0
    //   774: pop
    //   775: iconst_0
    //   776: ireturn
    //   777: aload 33
    //   779: checkcast 226	java/net/HttpURLConnection
    //   782: astore 34
    //   784: new 274	com/google/android/gms/internal/ads/md
    //   787: dup
    //   788: invokespecial 275	com/google/android/gms/internal/ads/md:<init>	()V
    //   791: astore 35
    //   793: aload 35
    //   795: aload 34
    //   797: aconst_null
    //   798: invokevirtual 278	com/google/android/gms/internal/ads/md:a	(Ljava/net/HttpURLConnection;[B)V
    //   801: aload 34
    //   803: iconst_0
    //   804: invokevirtual 282	java/net/HttpURLConnection:setInstanceFollowRedirects	(Z)V
    //   807: aload 34
    //   809: invokevirtual 285	java/net/HttpURLConnection:getResponseCode	()I
    //   812: istore 36
    //   814: aload 35
    //   816: aload 34
    //   818: iload 36
    //   820: invokevirtual 288	com/google/android/gms/internal/ads/md:a	(Ljava/net/HttpURLConnection;I)V
    //   823: iload 36
    //   825: bipush 100
    //   827: idiv
    //   828: iconst_3
    //   829: if_icmpne +209 -> 1038
    //   832: aload 34
    //   834: ldc_w 290
    //   837: invokevirtual 293	java/net/HttpURLConnection:getHeaderField	(Ljava/lang/String;)Ljava/lang/String;
    //   840: astore 80
    //   842: aload 80
    //   844: ifnonnull +14 -> 858
    //   847: new 114	java/io/IOException
    //   850: dup
    //   851: ldc_w 295
    //   854: invokespecial 229	java/io/IOException:<init>	(Ljava/lang/String;)V
    //   857: athrow
    //   858: new 210	java/net/URL
    //   861: dup
    //   862: aload 30
    //   864: aload 80
    //   866: invokespecial 298	java/net/URL:<init>	(Ljava/net/URL;Ljava/lang/String;)V
    //   869: astore 81
    //   871: aload 81
    //   873: invokevirtual 301	java/net/URL:getProtocol	()Ljava/lang/String;
    //   876: astore 82
    //   878: aload 82
    //   880: ifnonnull +14 -> 894
    //   883: new 114	java/io/IOException
    //   886: dup
    //   887: ldc_w 303
    //   890: invokespecial 229	java/io/IOException:<init>	(Ljava/lang/String;)V
    //   893: athrow
    //   894: aload 82
    //   896: ldc_w 305
    //   899: invokevirtual 308	java/lang/String:equals	(Ljava/lang/Object;)Z
    //   902: ifne +64 -> 966
    //   905: aload 82
    //   907: ldc_w 310
    //   910: invokevirtual 308	java/lang/String:equals	(Ljava/lang/Object;)Z
    //   913: ifne +53 -> 966
    //   916: aload 82
    //   918: invokestatic 83	java/lang/String:valueOf	(Ljava/lang/Object;)Ljava/lang/String;
    //   921: astore 85
    //   923: aload 85
    //   925: invokevirtual 87	java/lang/String:length	()I
    //   928: ifeq +23 -> 951
    //   931: ldc_w 312
    //   934: aload 85
    //   936: invokevirtual 93	java/lang/String:concat	(Ljava/lang/String;)Ljava/lang/String;
    //   939: astore 86
    //   941: new 114	java/io/IOException
    //   944: dup
    //   945: aload 86
    //   947: invokespecial 229	java/io/IOException:<init>	(Ljava/lang/String;)V
    //   950: athrow
    //   951: new 79	java/lang/String
    //   954: dup
    //   955: ldc_w 312
    //   958: invokespecial 94	java/lang/String:<init>	(Ljava/lang/String;)V
    //   961: astore 86
    //   963: goto -22 -> 941
    //   966: aload 80
    //   968: invokestatic 83	java/lang/String:valueOf	(Ljava/lang/Object;)Ljava/lang/String;
    //   971: astore 83
    //   973: aload 83
    //   975: invokevirtual 87	java/lang/String:length	()I
    //   978: ifeq +34 -> 1012
    //   981: ldc_w 314
    //   984: aload 83
    //   986: invokevirtual 93	java/lang/String:concat	(Ljava/lang/String;)Ljava/lang/String;
    //   989: astore 84
    //   991: aload 84
    //   993: invokestatic 183	com/google/android/gms/internal/ads/je:b	(Ljava/lang/String;)V
    //   996: aload 34
    //   998: invokevirtual 317	java/net/HttpURLConnection:disconnect	()V
    //   1001: iload 32
    //   1003: istore 31
    //   1005: aload 81
    //   1007: astore 30
    //   1009: goto -437 -> 572
    //   1012: new 79	java/lang/String
    //   1015: dup
    //   1016: ldc_w 314
    //   1019: invokespecial 94	java/lang/String:<init>	(Ljava/lang/String;)V
    //   1022: astore 84
    //   1024: goto -33 -> 991
    //   1027: new 114	java/io/IOException
    //   1030: dup
    //   1031: ldc_w 319
    //   1034: invokespecial 229	java/io/IOException:<init>	(Ljava/lang/String;)V
    //   1037: athrow
    //   1038: aload 34
    //   1040: instanceof 226
    //   1043: ifeq +141 -> 1184
    //   1046: aload 34
    //   1048: checkcast 226	java/net/HttpURLConnection
    //   1051: invokevirtual 285	java/net/HttpURLConnection:getResponseCode	()I
    //   1054: istore 77
    //   1056: iload 77
    //   1058: sipush 400
    //   1061: if_icmplt +123 -> 1184
    //   1064: ldc_w 321
    //   1067: astore 20
    //   1069: iload 77
    //   1071: invokestatic 324	java/lang/Integer:toString	(I)Ljava/lang/String;
    //   1074: invokestatic 83	java/lang/String:valueOf	(Ljava/lang/Object;)Ljava/lang/String;
    //   1077: astore 78
    //   1079: aload 78
    //   1081: invokevirtual 87	java/lang/String:length	()I
    //   1084: ifeq +74 -> 1158
    //   1087: ldc_w 326
    //   1090: aload 78
    //   1092: invokevirtual 93	java/lang/String:concat	(Ljava/lang/String;)Ljava/lang/String;
    //   1095: astore 79
    //   1097: aload 79
    //   1099: astore 21
    //   1101: new 114	java/io/IOException
    //   1104: dup
    //   1105: new 249	java/lang/StringBuilder
    //   1108: dup
    //   1109: bipush 32
    //   1111: aload_1
    //   1112: invokestatic 83	java/lang/String:valueOf	(Ljava/lang/Object;)Ljava/lang/String;
    //   1115: invokevirtual 87	java/lang/String:length	()I
    //   1118: iadd
    //   1119: invokespecial 251	java/lang/StringBuilder:<init>	(I)V
    //   1122: ldc_w 328
    //   1125: invokevirtual 257	java/lang/StringBuilder:append	(Ljava/lang/String;)Ljava/lang/StringBuilder;
    //   1128: iload 77
    //   1130: invokevirtual 331	java/lang/StringBuilder:append	(I)Ljava/lang/StringBuilder;
    //   1133: ldc_w 333
    //   1136: invokevirtual 257	java/lang/StringBuilder:append	(Ljava/lang/String;)Ljava/lang/StringBuilder;
    //   1139: aload_1
    //   1140: invokevirtual 257	java/lang/StringBuilder:append	(Ljava/lang/String;)Ljava/lang/StringBuilder;
    //   1143: invokevirtual 262	java/lang/StringBuilder:toString	()Ljava/lang/String;
    //   1146: invokespecial 229	java/io/IOException:<init>	(Ljava/lang/String;)V
    //   1149: athrow
    //   1150: astore 19
    //   1152: aconst_null
    //   1153: astore 18
    //   1155: goto -522 -> 633
    //   1158: new 79	java/lang/String
    //   1161: dup
    //   1162: ldc_w 326
    //   1165: invokespecial 94	java/lang/String:<init>	(Ljava/lang/String;)V
    //   1168: astore 21
    //   1170: goto -69 -> 1101
    //   1173: astore 19
    //   1175: aconst_null
    //   1176: astore 21
    //   1178: aconst_null
    //   1179: astore 18
    //   1181: goto -548 -> 633
    //   1184: aload 34
    //   1186: invokevirtual 336	java/net/URLConnection:getContentLength	()I
    //   1189: istore 37
    //   1191: iload 37
    //   1193: ifge +74 -> 1267
    //   1196: aload_1
    //   1197: invokestatic 83	java/lang/String:valueOf	(Ljava/lang/Object;)Ljava/lang/String;
    //   1200: astore 38
    //   1202: aload 38
    //   1204: invokevirtual 87	java/lang/String:length	()I
    //   1207: ifeq +45 -> 1252
    //   1210: ldc_w 338
    //   1213: aload 38
    //   1215: invokevirtual 93	java/lang/String:concat	(Ljava/lang/String;)Ljava/lang/String;
    //   1218: astore 39
    //   1220: aload 39
    //   1222: invokestatic 57	com/google/android/gms/internal/ads/je:e	(Ljava/lang/String;)V
    //   1225: aload_0
    //   1226: aload_1
    //   1227: aload 10
    //   1229: invokevirtual 77	java/io/File:getAbsolutePath	()Ljava/lang/String;
    //   1232: ldc_w 340
    //   1235: aconst_null
    //   1236: invokevirtual 123	com/google/android/gms/internal/ads/pp:a	(Ljava/lang/String;Ljava/lang/String;Ljava/lang/String;Ljava/lang/String;)V
    //   1239: getstatic 29	com/google/android/gms/internal/ads/pv:b	Ljava/util/Set;
    //   1242: aload 14
    //   1244: invokeinterface 272 2 0
    //   1249: pop
    //   1250: iconst_0
    //   1251: ireturn
    //   1252: new 79	java/lang/String
    //   1255: dup
    //   1256: ldc_w 338
    //   1259: invokespecial 94	java/lang/String:<init>	(Ljava/lang/String;)V
    //   1262: astore 39
    //   1264: goto -44 -> 1220
    //   1267: getstatic 38	com/google/android/gms/internal/ads/pv:c	Ljava/text/DecimalFormat;
    //   1270: iload 37
    //   1272: i2l
    //   1273: invokevirtual 344	java/text/DecimalFormat:format	(J)Ljava/lang/String;
    //   1276: astore 41
    //   1278: getstatic 347	com/google/android/gms/internal/ads/asa:o	Lcom/google/android/gms/internal/ads/arq;
    //   1281: astore 42
    //   1283: invokestatic 135	com/google/android/gms/internal/ads/aos:f	()Lcom/google/android/gms/internal/ads/ary;
    //   1286: aload 42
    //   1288: invokevirtual 140	com/google/android/gms/internal/ads/ary:a	(Lcom/google/android/gms/internal/ads/arq;)Ljava/lang/Object;
    //   1291: checkcast 142	java/lang/Integer
    //   1294: invokevirtual 145	java/lang/Integer:intValue	()I
    //   1297: istore 43
    //   1299: iload 37
    //   1301: iload 43
    //   1303: if_icmple +124 -> 1427
    //   1306: new 249	java/lang/StringBuilder
    //   1309: dup
    //   1310: bipush 33
    //   1312: aload 41
    //   1314: invokestatic 83	java/lang/String:valueOf	(Ljava/lang/Object;)Ljava/lang/String;
    //   1317: invokevirtual 87	java/lang/String:length	()I
    //   1320: iadd
    //   1321: aload_1
    //   1322: invokestatic 83	java/lang/String:valueOf	(Ljava/lang/Object;)Ljava/lang/String;
    //   1325: invokevirtual 87	java/lang/String:length	()I
    //   1328: iadd
    //   1329: invokespecial 251	java/lang/StringBuilder:<init>	(I)V
    //   1332: ldc_w 349
    //   1335: invokevirtual 257	java/lang/StringBuilder:append	(Ljava/lang/String;)Ljava/lang/StringBuilder;
    //   1338: aload 41
    //   1340: invokevirtual 257	java/lang/StringBuilder:append	(Ljava/lang/String;)Ljava/lang/StringBuilder;
    //   1343: ldc_w 351
    //   1346: invokevirtual 257	java/lang/StringBuilder:append	(Ljava/lang/String;)Ljava/lang/StringBuilder;
    //   1349: aload_1
    //   1350: invokevirtual 257	java/lang/StringBuilder:append	(Ljava/lang/String;)Ljava/lang/StringBuilder;
    //   1353: invokevirtual 262	java/lang/StringBuilder:toString	()Ljava/lang/String;
    //   1356: invokestatic 57	com/google/android/gms/internal/ads/je:e	(Ljava/lang/String;)V
    //   1359: aload 41
    //   1361: invokestatic 83	java/lang/String:valueOf	(Ljava/lang/Object;)Ljava/lang/String;
    //   1364: astore 44
    //   1366: aload 44
    //   1368: invokevirtual 87	java/lang/String:length	()I
    //   1371: ifeq +41 -> 1412
    //   1374: ldc_w 353
    //   1377: aload 44
    //   1379: invokevirtual 93	java/lang/String:concat	(Ljava/lang/String;)Ljava/lang/String;
    //   1382: astore 45
    //   1384: aload_0
    //   1385: aload_1
    //   1386: aload 10
    //   1388: invokevirtual 77	java/io/File:getAbsolutePath	()Ljava/lang/String;
    //   1391: ldc_w 355
    //   1394: aload 45
    //   1396: invokevirtual 123	com/google/android/gms/internal/ads/pp:a	(Ljava/lang/String;Ljava/lang/String;Ljava/lang/String;Ljava/lang/String;)V
    //   1399: getstatic 29	com/google/android/gms/internal/ads/pv:b	Ljava/util/Set;
    //   1402: aload 14
    //   1404: invokeinterface 272 2 0
    //   1409: pop
    //   1410: iconst_0
    //   1411: ireturn
    //   1412: new 79	java/lang/String
    //   1415: dup
    //   1416: ldc_w 353
    //   1419: invokespecial 94	java/lang/String:<init>	(Ljava/lang/String;)V
    //   1422: astore 45
    //   1424: goto -40 -> 1384
    //   1427: new 249	java/lang/StringBuilder
    //   1430: dup
    //   1431: bipush 20
    //   1433: aload 41
    //   1435: invokestatic 83	java/lang/String:valueOf	(Ljava/lang/Object;)Ljava/lang/String;
    //   1438: invokevirtual 87	java/lang/String:length	()I
    //   1441: iadd
    //   1442: aload_1
    //   1443: invokestatic 83	java/lang/String:valueOf	(Ljava/lang/Object;)Ljava/lang/String;
    //   1446: invokevirtual 87	java/lang/String:length	()I
    //   1449: iadd
    //   1450: invokespecial 251	java/lang/StringBuilder:<init>	(I)V
    //   1453: ldc_w 357
    //   1456: invokevirtual 257	java/lang/StringBuilder:append	(Ljava/lang/String;)Ljava/lang/StringBuilder;
    //   1459: aload 41
    //   1461: invokevirtual 257	java/lang/StringBuilder:append	(Ljava/lang/String;)Ljava/lang/StringBuilder;
    //   1464: ldc_w 359
    //   1467: invokevirtual 257	java/lang/StringBuilder:append	(Ljava/lang/String;)Ljava/lang/StringBuilder;
    //   1470: aload_1
    //   1471: invokevirtual 257	java/lang/StringBuilder:append	(Ljava/lang/String;)Ljava/lang/StringBuilder;
    //   1474: invokevirtual 262	java/lang/StringBuilder:toString	()Ljava/lang/String;
    //   1477: invokestatic 183	com/google/android/gms/internal/ads/je:b	(Ljava/lang/String;)V
    //   1480: aload 34
    //   1482: invokevirtual 363	java/net/URLConnection:getInputStream	()Ljava/io/InputStream;
    //   1485: invokestatic 369	java/nio/channels/Channels:newChannel	(Ljava/io/InputStream;)Ljava/nio/channels/ReadableByteChannel;
    //   1488: astore 47
    //   1490: new 244	java/io/FileOutputStream
    //   1493: dup
    //   1494: aload 10
    //   1496: invokespecial 372	java/io/FileOutputStream:<init>	(Ljava/io/File;)V
    //   1499: astore 48
    //   1501: aload 48
    //   1503: invokevirtual 376	java/io/FileOutputStream:getChannel	()Ljava/nio/channels/FileChannel;
    //   1506: astore 49
    //   1508: ldc_w 377
    //   1511: invokestatic 383	java/nio/ByteBuffer:allocate	(I)Ljava/nio/ByteBuffer;
    //   1514: astore 50
    //   1516: invokestatic 387	com/google/android/gms/ads/internal/zzbv:zzer	()Lcom/google/android/gms/common/util/c;
    //   1519: astore 51
    //   1521: iconst_0
    //   1522: istore 52
    //   1524: aload 51
    //   1526: invokeinterface 391 1 0
    //   1531: lstore 53
    //   1533: getstatic 394	com/google/android/gms/internal/ads/asa:r	Lcom/google/android/gms/internal/ads/arq;
    //   1536: astore 55
    //   1538: invokestatic 135	com/google/android/gms/internal/ads/aos:f	()Lcom/google/android/gms/internal/ads/ary;
    //   1541: aload 55
    //   1543: invokevirtual 140	com/google/android/gms/internal/ads/ary:a	(Lcom/google/android/gms/internal/ads/arq;)Ljava/lang/Object;
    //   1546: checkcast 396	java/lang/Long
    //   1549: invokevirtual 399	java/lang/Long:longValue	()J
    //   1552: lstore 56
    //   1554: new 401	com/google/android/gms/internal/ads/lo
    //   1557: dup
    //   1558: lload 56
    //   1560: invokespecial 404	com/google/android/gms/internal/ads/lo:<init>	(J)V
    //   1563: astore 58
    //   1565: getstatic 407	com/google/android/gms/internal/ads/asa:q	Lcom/google/android/gms/internal/ads/arq;
    //   1568: astore 59
    //   1570: invokestatic 135	com/google/android/gms/internal/ads/aos:f	()Lcom/google/android/gms/internal/ads/ary;
    //   1573: aload 59
    //   1575: invokevirtual 140	com/google/android/gms/internal/ads/ary:a	(Lcom/google/android/gms/internal/ads/arq;)Ljava/lang/Object;
    //   1578: checkcast 396	java/lang/Long
    //   1581: invokevirtual 399	java/lang/Long:longValue	()J
    //   1584: lstore 60
    //   1586: aload 47
    //   1588: aload 50
    //   1590: invokeinterface 413 2 0
    //   1595: istore 62
    //   1597: iload 62
    //   1599: iflt +295 -> 1894
    //   1602: iload 52
    //   1604: iload 62
    //   1606: iadd
    //   1607: istore 52
    //   1609: iload 52
    //   1611: iload 43
    //   1613: if_icmple +87 -> 1700
    //   1616: ldc_w 355
    //   1619: astore 20
    //   1621: iload 52
    //   1623: invokestatic 324	java/lang/Integer:toString	(I)Ljava/lang/String;
    //   1626: invokestatic 83	java/lang/String:valueOf	(Ljava/lang/Object;)Ljava/lang/String;
    //   1629: astore 75
    //   1631: aload 75
    //   1633: invokevirtual 87	java/lang/String:length	()I
    //   1636: ifeq +37 -> 1673
    //   1639: ldc_w 353
    //   1642: aload 75
    //   1644: invokevirtual 93	java/lang/String:concat	(Ljava/lang/String;)Ljava/lang/String;
    //   1647: astore 76
    //   1649: aload 76
    //   1651: astore 21
    //   1653: new 114	java/io/IOException
    //   1656: dup
    //   1657: ldc_w 415
    //   1660: invokespecial 229	java/io/IOException:<init>	(Ljava/lang/String;)V
    //   1663: athrow
    //   1664: astore 19
    //   1666: aload 48
    //   1668: astore 18
    //   1670: goto -1037 -> 633
    //   1673: new 79	java/lang/String
    //   1676: dup
    //   1677: ldc_w 353
    //   1680: invokespecial 94	java/lang/String:<init>	(Ljava/lang/String;)V
    //   1683: astore 21
    //   1685: goto -32 -> 1653
    //   1688: astore 19
    //   1690: aload 48
    //   1692: astore 18
    //   1694: aconst_null
    //   1695: astore 21
    //   1697: goto -1064 -> 633
    //   1700: aload 50
    //   1702: invokevirtual 419	java/nio/ByteBuffer:flip	()Ljava/nio/Buffer;
    //   1705: pop
    //   1706: aload 49
    //   1708: aload 50
    //   1710: invokevirtual 424	java/nio/channels/FileChannel:write	(Ljava/nio/ByteBuffer;)I
    //   1713: ifgt -7 -> 1706
    //   1716: aload 50
    //   1718: invokevirtual 427	java/nio/ByteBuffer:clear	()Ljava/nio/Buffer;
    //   1721: pop
    //   1722: aload 51
    //   1724: invokeinterface 391 1 0
    //   1729: lload 53
    //   1731: lsub
    //   1732: ldc2_w 428
    //   1735: lload 60
    //   1737: lmul
    //   1738: lcmp
    //   1739: ifle +79 -> 1818
    //   1742: ldc_w 431
    //   1745: astore 20
    //   1747: lload 60
    //   1749: invokestatic 433	java/lang/Long:toString	(J)Ljava/lang/String;
    //   1752: astore 71
    //   1754: new 249	java/lang/StringBuilder
    //   1757: dup
    //   1758: bipush 29
    //   1760: aload 71
    //   1762: invokestatic 83	java/lang/String:valueOf	(Ljava/lang/Object;)Ljava/lang/String;
    //   1765: invokevirtual 87	java/lang/String:length	()I
    //   1768: iadd
    //   1769: invokespecial 251	java/lang/StringBuilder:<init>	(I)V
    //   1772: ldc_w 435
    //   1775: invokevirtual 257	java/lang/StringBuilder:append	(Ljava/lang/String;)Ljava/lang/StringBuilder;
    //   1778: aload 71
    //   1780: invokevirtual 257	java/lang/StringBuilder:append	(Ljava/lang/String;)Ljava/lang/StringBuilder;
    //   1783: ldc_w 437
    //   1786: invokevirtual 257	java/lang/StringBuilder:append	(Ljava/lang/String;)Ljava/lang/StringBuilder;
    //   1789: invokevirtual 262	java/lang/StringBuilder:toString	()Ljava/lang/String;
    //   1792: astore 72
    //   1794: aload 72
    //   1796: astore 21
    //   1798: new 114	java/io/IOException
    //   1801: dup
    //   1802: ldc_w 439
    //   1805: invokespecial 229	java/io/IOException:<init>	(Ljava/lang/String;)V
    //   1808: athrow
    //   1809: astore 19
    //   1811: aload 48
    //   1813: astore 18
    //   1815: goto -1182 -> 633
    //   1818: aload_0
    //   1819: getfield 111	com/google/android/gms/internal/ads/pv:e	Z
    //   1822: ifeq +31 -> 1853
    //   1825: ldc_w 441
    //   1828: astore 20
    //   1830: new 114	java/io/IOException
    //   1833: dup
    //   1834: ldc_w 443
    //   1837: invokespecial 229	java/io/IOException:<init>	(Ljava/lang/String;)V
    //   1840: athrow
    //   1841: astore 19
    //   1843: aload 48
    //   1845: astore 18
    //   1847: aconst_null
    //   1848: astore 21
    //   1850: goto -1217 -> 633
    //   1853: aload 58
    //   1855: invokevirtual 445	com/google/android/gms/internal/ads/lo:a	()Z
    //   1858: ifeq -272 -> 1586
    //   1861: aload 10
    //   1863: invokevirtual 77	java/io/File:getAbsolutePath	()Ljava/lang/String;
    //   1866: astore 73
    //   1868: getstatic 448	com/google/android/gms/internal/ads/lz:a	Landroid/os/Handler;
    //   1871: new 450	com/google/android/gms/internal/ads/pq
    //   1874: dup
    //   1875: aload_0
    //   1876: aload_1
    //   1877: aload 73
    //   1879: iload 52
    //   1881: iload 37
    //   1883: iconst_0
    //   1884: invokespecial 453	com/google/android/gms/internal/ads/pq:<init>	(Lcom/google/android/gms/internal/ads/pp;Ljava/lang/String;Ljava/lang/String;IIZ)V
    //   1887: invokevirtual 459	android/os/Handler:post	(Ljava/lang/Runnable;)Z
    //   1890: pop
    //   1891: goto -305 -> 1586
    //   1894: aload 48
    //   1896: invokevirtual 247	java/io/FileOutputStream:close	()V
    //   1899: iconst_3
    //   1900: invokestatic 462	com/google/android/gms/internal/ads/je:a	(I)Z
    //   1903: ifeq +67 -> 1970
    //   1906: getstatic 38	com/google/android/gms/internal/ads/pv:c	Ljava/text/DecimalFormat;
    //   1909: iload 52
    //   1911: i2l
    //   1912: invokevirtual 344	java/text/DecimalFormat:format	(J)Ljava/lang/String;
    //   1915: astore 68
    //   1917: new 249	java/lang/StringBuilder
    //   1920: dup
    //   1921: bipush 22
    //   1923: aload 68
    //   1925: invokestatic 83	java/lang/String:valueOf	(Ljava/lang/Object;)Ljava/lang/String;
    //   1928: invokevirtual 87	java/lang/String:length	()I
    //   1931: iadd
    //   1932: aload_1
    //   1933: invokestatic 83	java/lang/String:valueOf	(Ljava/lang/Object;)Ljava/lang/String;
    //   1936: invokevirtual 87	java/lang/String:length	()I
    //   1939: iadd
    //   1940: invokespecial 251	java/lang/StringBuilder:<init>	(I)V
    //   1943: ldc_w 464
    //   1946: invokevirtual 257	java/lang/StringBuilder:append	(Ljava/lang/String;)Ljava/lang/StringBuilder;
    //   1949: aload 68
    //   1951: invokevirtual 257	java/lang/StringBuilder:append	(Ljava/lang/String;)Ljava/lang/StringBuilder;
    //   1954: ldc_w 359
    //   1957: invokevirtual 257	java/lang/StringBuilder:append	(Ljava/lang/String;)Ljava/lang/StringBuilder;
    //   1960: aload_1
    //   1961: invokevirtual 257	java/lang/StringBuilder:append	(Ljava/lang/String;)Ljava/lang/StringBuilder;
    //   1964: invokevirtual 262	java/lang/StringBuilder:toString	()Ljava/lang/String;
    //   1967: invokestatic 183	com/google/android/gms/internal/ads/je:b	(Ljava/lang/String;)V
    //   1970: aload 10
    //   1972: iconst_1
    //   1973: iconst_0
    //   1974: invokevirtual 98	java/io/File:setReadable	(ZZ)Z
    //   1977: pop
    //   1978: aload 11
    //   1980: invokevirtual 170	java/io/File:isFile	()Z
    //   1983: ifeq +37 -> 2020
    //   1986: aload 11
    //   1988: invokestatic 469	java/lang/System:currentTimeMillis	()J
    //   1991: invokevirtual 473	java/io/File:setLastModified	(J)Z
    //   1994: pop
    //   1995: aload_0
    //   1996: aload_1
    //   1997: aload 10
    //   1999: invokevirtual 77	java/io/File:getAbsolutePath	()Ljava/lang/String;
    //   2002: iload 52
    //   2004: invokevirtual 186	com/google/android/gms/internal/ads/pp:a	(Ljava/lang/String;Ljava/lang/String;I)V
    //   2007: getstatic 29	com/google/android/gms/internal/ads/pv:b	Ljava/util/Set;
    //   2010: aload 14
    //   2012: invokeinterface 272 2 0
    //   2017: pop
    //   2018: iconst_1
    //   2019: ireturn
    //   2020: aload 11
    //   2022: invokevirtual 476	java/io/File:createNewFile	()Z
    //   2025: pop
    //   2026: goto -31 -> 1995
    //   2029: astore 64
    //   2031: goto -36 -> 1995
    //   2034: new 249	java/lang/StringBuilder
    //   2037: dup
    //   2038: bipush 25
    //   2040: aload_1
    //   2041: invokestatic 83	java/lang/String:valueOf	(Ljava/lang/Object;)Ljava/lang/String;
    //   2044: invokevirtual 87	java/lang/String:length	()I
    //   2047: iadd
    //   2048: invokespecial 251	java/lang/StringBuilder:<init>	(I)V
    //   2051: ldc_w 478
    //   2054: invokevirtual 257	java/lang/StringBuilder:append	(Ljava/lang/String;)Ljava/lang/StringBuilder;
    //   2057: aload_1
    //   2058: invokevirtual 257	java/lang/StringBuilder:append	(Ljava/lang/String;)Ljava/lang/StringBuilder;
    //   2061: ldc_w 259
    //   2064: invokevirtual 257	java/lang/StringBuilder:append	(Ljava/lang/String;)Ljava/lang/StringBuilder;
    //   2067: invokevirtual 262	java/lang/StringBuilder:toString	()Ljava/lang/String;
    //   2070: aload 19
    //   2072: invokestatic 481	com/google/android/gms/internal/ads/je:c	(Ljava/lang/String;Ljava/lang/Throwable;)V
    //   2075: goto -1374 -> 701
    //   2078: new 79	java/lang/String
    //   2081: dup
    //   2082: ldc_w 269
    //   2085: invokespecial 94	java/lang/String:<init>	(Ljava/lang/String;)V
    //   2088: astore 25
    //   2090: goto -1345 -> 745
    //   2093: astore 26
    //   2095: goto -1439 -> 656
    //   2098: astore 22
    //   2100: goto -1444 -> 656
    //   2103: astore 19
    //   2105: aconst_null
    //   2106: astore 21
    //   2108: aconst_null
    //   2109: astore 18
    //   2111: goto -1478 -> 633
    //   2114: astore 19
    //   2116: aconst_null
    //   2117: astore 18
    //   2119: goto -1486 -> 633
    //   2122: astore 19
    //   2124: ldc 231
    //   2126: astore 20
    //   2128: aload 48
    //   2130: astore 18
    //   2132: aconst_null
    //   2133: astore 21
    //   2135: goto -1502 -> 633
    //   2138: lload 93
    //   2140: lstore 101
    //   2142: aload 92
    //   2144: astore 103
    //   2146: goto -1938 -> 208
    //   2149: astore 19
    //   2151: ldc 231
    //   2153: astore 20
    //   2155: aconst_null
    //   2156: astore 21
    //   2158: aconst_null
    //   2159: astore 18
    //   2161: goto -1528 -> 633
    //   2164: astore 19
    //   2166: ldc 231
    //   2168: astore 20
    //   2170: aload 48
    //   2172: astore 18
    //   2174: aconst_null
    //   2175: astore 21
    //   2177: goto -1544 -> 633
    // Local variable table:
    //   start	length	slot	name	signature
    //   0	2180	0	this	pv
    //   0	2180	1	paramString	String
    //   90	17	2	arrayOfFile1	File[]
    //   93	11	3	i	int
    //   95	36	4	j	int
    //   98	27	5	k	int
    //   26	107	6	m	int
    //   31	8	7	localarq1	arq
    //   274	11	9	str1	String
    //   289	1709	10	localFile1	File
    //   297	1724	11	localFile2	File
    //   389	105	12	str2	String
    //   395	13	13	str3	String
    //   412	1599	14	str4	String
    //   417	112	15	localSet	Set
    //   481	6	16	localObject1	java.lang.Object
    //   532	1641	18	localObject2	java.lang.Object
    //   624	21	19	localIOException1	java.io.IOException
    //   1150	1	19	localIOException2	java.io.IOException
    //   1173	1	19	localIOException3	java.io.IOException
    //   1664	1	19	localIOException4	java.io.IOException
    //   1688	1	19	localIOException5	java.io.IOException
    //   1809	1	19	localRuntimeException1	java.lang.RuntimeException
    //   1841	230	19	localRuntimeException2	java.lang.RuntimeException
    //   2103	1	19	localRuntimeException3	java.lang.RuntimeException
    //   2114	1	19	localRuntimeException4	java.lang.RuntimeException
    //   2122	1	19	localRuntimeException5	java.lang.RuntimeException
    //   2149	1	19	localRuntimeException6	java.lang.RuntimeException
    //   2164	1	19	localIOException6	java.io.IOException
    //   631	1538	20	str5	String
    //   627	1549	21	localObject3	java.lang.Object
    //   2098	1	22	localNullPointerException	java.lang.NullPointerException
    //   725	14	24	str6	String
    //   743	1346	25	str7	String
    //   2093	1	26	localIOException7	java.io.IOException
    //   541	6	28	localarq2	arq
    //   557	45	29	n	int
    //   567	441	30	localObject4	java.lang.Object
    //   570	434	31	i1	int
    //   576	426	32	i2	int
    //   590	188	33	localURLConnection	java.net.URLConnection
    //   782	699	34	localHttpURLConnection	java.net.HttpURLConnection
    //   791	24	35	localmd	md
    //   812	16	36	i3	int
    //   1189	693	37	i4	int
    //   1200	14	38	str8	String
    //   1218	45	39	str9	String
    //   1276	184	41	str10	String
    //   1281	6	42	localarq3	arq
    //   1297	317	43	i5	int
    //   1364	14	44	str11	String
    //   1382	41	45	str12	String
    //   1488	99	47	localReadableByteChannel	java.nio.channels.ReadableByteChannel
    //   1499	672	48	localFileOutputStream	java.io.FileOutputStream
    //   1506	201	49	localFileChannel	java.nio.channels.FileChannel
    //   1514	203	50	localByteBuffer	java.nio.ByteBuffer
    //   1519	204	51	localc	com.google.android.gms.common.util.c
    //   1522	481	52	i6	int
    //   1531	199	53	l1	long
    //   1536	6	55	localarq4	arq
    //   1552	7	56	l2	long
    //   1563	291	58	locallo	lo
    //   1568	6	59	localarq5	arq
    //   1584	164	60	l3	long
    //   1595	12	62	i7	int
    //   2029	1	64	localIOException8	java.io.IOException
    //   1915	35	68	str13	String
    //   1752	27	71	str14	String
    //   1792	3	72	str15	String
    //   1866	12	73	str16	String
    //   1629	14	75	str17	String
    //   1647	3	76	str18	String
    //   1054	75	77	i8	int
    //   1077	14	78	str19	String
    //   1095	3	79	str20	String
    //   840	127	80	str21	String
    //   869	137	81	localURL	java.net.URL
    //   876	41	82	str22	String
    //   971	14	83	str23	String
    //   989	34	84	str24	String
    //   921	14	85	str25	String
    //   939	23	86	str26	String
    //   439	13	87	str27	String
    //   456	57	88	str28	String
    //   321	38	89	i9	int
    //   327	13	90	str29	String
    //   344	31	91	str30	String
    //   138	2005	92	localObject5	java.lang.Object
    //   143	1996	93	l4	long
    //   152	18	95	arrayOfFile2	File[]
    //   157	10	96	i10	int
    //   160	49	97	i11	int
    //   60	202	98	bool	boolean
    //   243	13	99	localFile3	File
    //   174	31	100	localFile4	File
    //   194	1947	101	l5	long
    //   206	1939	103	localObject6	java.lang.Object
    // Exception table:
    //   from	to	target	type
    //   422	458	481	finally
    //   458	479	481	finally
    //   483	486	481	finally
    //   503	514	481	finally
    //   517	531	481	finally
    //   534	569	624	java/io/IOException
    //   585	624	624	java/io/IOException
    //   777	842	624	java/io/IOException
    //   847	858	624	java/io/IOException
    //   858	878	624	java/io/IOException
    //   883	894	624	java/io/IOException
    //   894	941	624	java/io/IOException
    //   941	951	624	java/io/IOException
    //   951	963	624	java/io/IOException
    //   966	991	624	java/io/IOException
    //   991	1001	624	java/io/IOException
    //   1012	1024	624	java/io/IOException
    //   1027	1038	624	java/io/IOException
    //   1038	1056	624	java/io/IOException
    //   1184	1191	624	java/io/IOException
    //   1196	1220	624	java/io/IOException
    //   1220	1250	624	java/io/IOException
    //   1252	1264	624	java/io/IOException
    //   1267	1299	624	java/io/IOException
    //   1306	1384	624	java/io/IOException
    //   1384	1410	624	java/io/IOException
    //   1412	1424	624	java/io/IOException
    //   1427	1501	624	java/io/IOException
    //   1101	1150	1150	java/io/IOException
    //   1069	1097	1173	java/io/IOException
    //   1158	1170	1173	java/io/IOException
    //   1653	1664	1664	java/io/IOException
    //   1798	1809	1664	java/io/IOException
    //   1621	1649	1688	java/io/IOException
    //   1673	1685	1688	java/io/IOException
    //   1747	1794	1688	java/io/IOException
    //   1830	1841	1688	java/io/IOException
    //   1653	1664	1809	java/lang/RuntimeException
    //   1798	1809	1809	java/lang/RuntimeException
    //   1621	1649	1841	java/lang/RuntimeException
    //   1673	1685	1841	java/lang/RuntimeException
    //   1747	1794	1841	java/lang/RuntimeException
    //   1830	1841	1841	java/lang/RuntimeException
    //   2020	2026	2029	java/io/IOException
    //   651	656	2093	java/io/IOException
    //   651	656	2098	java/lang/NullPointerException
    //   1069	1097	2103	java/lang/RuntimeException
    //   1158	1170	2103	java/lang/RuntimeException
    //   1101	1150	2114	java/lang/RuntimeException
    //   1501	1521	2122	java/lang/RuntimeException
    //   1524	1586	2122	java/lang/RuntimeException
    //   1586	1597	2122	java/lang/RuntimeException
    //   1700	1706	2122	java/lang/RuntimeException
    //   1706	1742	2122	java/lang/RuntimeException
    //   1818	1825	2122	java/lang/RuntimeException
    //   1853	1891	2122	java/lang/RuntimeException
    //   1894	1970	2122	java/lang/RuntimeException
    //   1970	1995	2122	java/lang/RuntimeException
    //   1995	2018	2122	java/lang/RuntimeException
    //   2020	2026	2122	java/lang/RuntimeException
    //   534	569	2149	java/lang/RuntimeException
    //   585	624	2149	java/lang/RuntimeException
    //   777	842	2149	java/lang/RuntimeException
    //   847	858	2149	java/lang/RuntimeException
    //   858	878	2149	java/lang/RuntimeException
    //   883	894	2149	java/lang/RuntimeException
    //   894	941	2149	java/lang/RuntimeException
    //   941	951	2149	java/lang/RuntimeException
    //   951	963	2149	java/lang/RuntimeException
    //   966	991	2149	java/lang/RuntimeException
    //   991	1001	2149	java/lang/RuntimeException
    //   1012	1024	2149	java/lang/RuntimeException
    //   1027	1038	2149	java/lang/RuntimeException
    //   1038	1056	2149	java/lang/RuntimeException
    //   1184	1191	2149	java/lang/RuntimeException
    //   1196	1220	2149	java/lang/RuntimeException
    //   1220	1250	2149	java/lang/RuntimeException
    //   1252	1264	2149	java/lang/RuntimeException
    //   1267	1299	2149	java/lang/RuntimeException
    //   1306	1384	2149	java/lang/RuntimeException
    //   1384	1410	2149	java/lang/RuntimeException
    //   1412	1424	2149	java/lang/RuntimeException
    //   1427	1501	2149	java/lang/RuntimeException
    //   1501	1521	2164	java/io/IOException
    //   1524	1586	2164	java/io/IOException
    //   1586	1597	2164	java/io/IOException
    //   1700	1706	2164	java/io/IOException
    //   1706	1742	2164	java/io/IOException
    //   1818	1825	2164	java/io/IOException
    //   1853	1891	2164	java/io/IOException
    //   1894	1970	2164	java/io/IOException
    //   1970	1995	2164	java/io/IOException
    //   1995	2018	2164	java/io/IOException
  }
}


/* Location:           C:\Users\IrfanRZ\Desktop\video walp\classes_dex2jar.jar
 * Qualified Name:     com.google.android.gms.internal.ads.pv
 * JD-Core Version:    0.7.0.1
 */